Workbook

Sheet PART I (CY 2024&SY2024-2025)
B2: OFFICE PERFORMANCE COMMITMENT AND REVIEW FORM (OPCRF) ver.Feb2025
B4: Name of Employee: | N4: Name of Rater:
B5: Position/Designation: | N5: Position:
B6: Review Period: | N6: Approving Authority:
B7: Strand/Bureau/Center/Service/Region/Division: | N7: Date of Review:
B8: Strand/Bureau/Center/Service/Region/Division Statement of Purpose:
B10: PART I-A: COMMITMENT TO ORGANIZATIONAL OUTCOMES (60%) Part I-A. Commitment to Organizational Outcomes shall capture office commitments, performance, and accomplishments based on office mandates and KRAs as reflected in the official issuance on the Compendium of Office Functions. This part shall capture the contributions of the office directly targeting the Organizational Outcomes indicated in the General Appropriation Act (GAA) Programs/Subprograms, Basic Education Development Plan (BEDP) Pillars, MATATAG Agenda priority deliverables, and other national level commitments that are aligned with and relevant to the office KRAs. Clear attribution shall be made to ensure such alignment.
B12: TO BE ACCOMPLISHED DURING PLANNING | S12: TO BE FILLED DURING EVALUATION
B13: Organizational Outcomes Alignment | F13: Objectives (based on Office Functions) | H13: Timeline | I13: Weight Allocation | J13: Performance Targets (Target Outcome/Ouput of the Bureau/Center/Service/Division aligned with the Outcome/Output Indicators in the Organizational Outcomes) | L13: Performance Measure (Quality, Efficiency, Timeliness) | M13: Rating Scale | R13: Means of Verification (MOVs) | S13: Actual Accomplishments | T13: RATING (Q,E,T) | U13: AVERAGE (QET) | V13: WEIGHTED AVERAGE
B14: Key Result Areas (KRA) (Based on Office Mandate and Functions) | C14: Organizational Outcome Attribution (Refer to the GAA Programs/Subprogram and BEDP Pillars) | J14: Value (numerical, statistical, trend) | K14: Description (expected outcome/ output/service) | M14: 5 (Outstanding) | N14: 4 (Very Satisfactory) | O14: 3 (Satisfactory) | P14: 2 (Unsatisfactory) | Q14: 1 (Poor)
C15: GAA Programs/ Subprograms | D15: BEDP Pillars | E15: MATATAG Pillars
B16: Education Human Resource Development Program | E16: X number of policies formulated, reviewed, and issued | F16: Human Resource Development | G16: Objective 1: Ensured preparation of HR policies, guidelines, and standards that are Bureau-initiated, or may be assigned by the EXECOM for issuance; compliant with PRIME-HRM standards and national guidelines geared towards competency-based HR system within the set scheduled deadline. | H16: January to December 2024 | I16: 0.35 | L16: Quality | M16: Met all 5 indicators based on the established standards in policy formulation: a. Consistent with existing laws, policies, guidelines, requirements, and data/information as may be required by law, oversight agencies, and/or DepEd b. Consistent with agency strategic directions and appropriate with DepEd context c. Compliant with DepEd guidelines on policy development process and underwent consultations and involvement of relevant management officials, personnel, and stakeholders at all governance levels d. Provided presentation materials, press release(as needed), and briefers for Directors and Executive sponsors e. Provided with complete staff work, to include implications/scenario analysis and recommendations | N16: Met 4 out of 5 indicators based on the established standards in policy formulation | O16: Met 3 out of 5 indicators based on the established standards in policy formulation | P16: Met 2 out of 5 indicators based on the established standards in policy formulation | Q16: Only 1 out of 5 indicators is met based on the established standards in policy formulation | S16: Policy deliverables submitted followed the set standards in policy formulation and met all 5 indicators | T16: 5 | U16: =AVERAGE(T16:T18) -> 4.6666667
L17: Efficiency | M17: 100% of total number of policy deliverables submitted and/or presented to the Director for approval; commented upon by such and provided responses to said comments; and/or integrated into the proposed policy action document. | N17: 76-99% of total number of policy deliverables submitted and/or presented to the Director for approval; commented upon by such and provided responses to said comments; and/or integrated into the proposed policy action document. | O17: 51-75% of total number of policy deliverables submitted and/or presented to the Director for approval; commented upon by such and provided responses to said comments; and/or integrated into the proposed policy action document. | P17: 26-50% of total number of policy deliverables submitted and/or presented to the Director for approval; commented upon by such and provided responses to said comments; and/or integrated into the proposed policy action document. | Q17: 25 %and below of total number of policy deliverables submitted and/or presented to the Director for approval; commented upon by such and provided responses to said comments; and/or integrated into the proposed policy action document. | S17: 13 out of 15 (87%) policy deliverables were submitted and/or presented to the Director and/or EXECOM for approval | T17: 4
L18: Timeliness | M18: Endorsed to the Office of the Director before the deadline set | N18: Endorsed to the Office of the Director on the deadline set | O18: Endorsed to the Office of the Director two weeks after the deadline | P18: Endorsed to the Office of the Director one month after the deadline | Q18: Endorsed to the Office of the Director more than one month | S18: 13 policy deliberables endorsed to the Office of the Director before the deadline set | T18: 5
C19: Refer to Accountability Matrix (PREXC Indicators) | D19: Refer to BMEF and BEDP 2030 | L19: Quality | U19: =AVERAGE(T19:T21) -> #DIV/0! | V19: =U19*I19 -> #DIV/0!
L20: Efficiency
L21: Timeliness
L22: Quality | U22: =AVERAGE(T22:T24) -> #DIV/0! | V22: =U22*I22 -> #DIV/0!
L23: Efficiency
L24: Timeliness
L25: Quality | U25: =AVERAGE(T25:T27) -> #DIV/0! | V25: =U25*I25 -> #DIV/0!
L26: Efficiency
L27: Timeliness
R37: Part I-A Total Score | V37: =SUM(V19:V27) -> #DIV/0!
B40: PART I-B: INNOVATING AND INTERVENING ACCOMPLISHMENTS (20%) Part I-B. Innovating and Intervening Accomplishments shall capture the outcomes/outputs of the office that are enabling, supportive, and/or contributory to the achievement of the organizational commitments and KRAs in Part I-A. Accomplishments can be innovations, interventions, and enhancements on the processes, services, and/or outputs.
B41: TO BE FILLED IN DURING PLANNING | S41: TO BE FILLED DURING EVALUATION
B42: Key Result Areas (KRA) | F42: Objectives | H42: Timeline | I42: Weight Allocation | J42: Performance Targets (Target Outcome/Ouput of the Bureau/Center/Service/Division that are enabling, supportive, and/or contributory to the achievement of the organizational outcomes and KRAs (Part I-A)) | L42: Performance Measure (Quality, Efficiency, Timeliness) | M42: RATING SCALE | R42: Means of Verification (MOVs) | S42: Actual Results/ Accomplishments | T42: RATING (Q,E,T) | U42: AVERAGE (QET) | V42: WEIGHTED AVERAGE
J43: Value (numerical, statistical, trend) | K43: Description (expected outcome/ output/service) | M43: 5 (Outstanding) | N43: 4 (Very Satisfactory) | O43: 3 (Satisfactory) | P43: 2 (Unsatisfactory) | Q43: 1 (Poor)
L44: Quality | U44: =AVERAGE(T44:T46) -> #DIV/0! | V44: =U44*I44 -> #DIV/0!
L45: Efficiency
L46: Timeliness
L47: Quality | U47: =AVERAGE(T47:T49) -> #DIV/0! | V47: =U47*I47 -> #DIV/0!
L48: Efficiency
L49: Timeliness
L50: Quality | U50: =AVERAGE(T50:T52) -> #DIV/0! | V50: =U50*I50 -> #DIV/0!
L51: Efficiency
L52: Timeliness
B71: Part I-B Total Score | V71: =SUM(V44:V52) -> #DIV/0!
B73: PART I-C: ORGANIZATIONAL EFFECTIVENESS (15%) Part I-C. Organizational Effectiveness shall capture accomplishments/outputs produced or attained on the aspects of Financial Stewardship, Process Improvement, and Client Satisfaction. It shall focus on the results achieved by the office that are aligned with the Performance-based Bonus (PBB) oversight requirements.
B75: TO BE FILLED IN DURING PLANNING | S75: TO BE FILLED DURING EVALUATION
B76: Organizational Effectiveness Area | F76: Objectives | J76: Timeline | K76: Weight Allocation | L76: Performance Measure (Quality, Efficiency, Timeliness) | M76: RATING SCALE | R76: Means of Verification (MOVs) | S76: Actual Results/ Accomplishments | T76: RATING (Q,E,T) | U76: AVERAGE (QET) | V76: WEIGHTED AVERAGE
M77: 5 (Outstanding) | N77: 4 (Very Satisfactory) | O77: 3 (Satisfactory) | P77: 2 (Unsatisfactory) | Q77: 1 (Poor)
B78: Financial Stewardship | F78: Utilized 98% of the budget allocation in accordance with the quarterly disbursement program with no overdraft/deficit/disallowance from oversight agency/ies | J78: Within the rating period | K78: 0.05 | L78: Quality | M78: Budget allocation disbursed within the reglementary period with no overdraft/deficit/disallowance from oversight agency/ies | N78: Budget allocation disbursed within the reglementary period with 1-2 overdraft/deficit/disallowance from oversight agency/ies | O78: Budget allocation disbursed within the reglementary period with 3-4 overdraft/deficit/disallowance from oversight agency/ies | P78: Budget allocation disbursed within the reglementary period with 5-6 overdraft/deficit/disallowance from oversight agency/ies | Q78: Budget allocation disbursed within the reglementary period with 7 or more overdraft/deficit/disallowance from oversight agency/ies | U78: =AVERAGE(T78:T80) -> #DIV/0! | V78: =U78*K78 -> #DIV/0!
L79: Efficiency | M79: Budget is utilized according to the BUR target, based on the official BUR report of the Finance Service/Section/Unit (i.e. 98% of the budget allocation is utilized within the FY) | N79: Budget is utilized with 1-5% variance from BUR target, based on the official BUR report of the Finance Service/Section/Unit (i.e. 93-97% of the budget allocation is utilized within the FY) | O79: Budget is utilized with 6-10% variance from BUR target, based on the official BUR report of the Finance Service/Section/Unit (i.e. 88-92% of the budget allocation is utilized within the FY) | P79: Budget is utilized with 11-15% variance from BUR target, based on the official BUR report of the Finance Service/Section/Unit (i.e. 83-87% of the budget allocation is utilized within the FY) | Q79: Budget is utilized with more than 15% variance from BUR target, based on the official BUR report of the Finance Service/Section/Unit (i.e. Below 83% of the budget allocation is utilized within the FY)
L80: Timeliness | M80: Quarterly basis: Budget is utilized according to the quarterly disbursement program (i.e. 98% of the quarterly BUR target is utilized by the end of each quarter) | N80: Quarterly basis: Budget is utilized with 1-5% variance from the quarterly disbursement program (i.e. 93-97% of the quarterly BUR target is utilized by the end of each quarter) | O80: Quarterly basis: Budget is utilized with 6-10% variance from the quarterly disbursement program (i.e. 88-92% of the quarterly BUR target is utilized by the end of each quarter) | P80: Quarterly basis: Budget is utilized with 11-15% variance from the quarterly disbursement program (i.e. 83-87% of the quarterly BUR target is utilized by the end of each quarter) | Q80: Quarterly basis: Budget is utilized with more than 15% variance from the quarterly disbursement program (i.e. Below 83% of the quarterly BUR target is utilized by the end of each quarter)
B81: Process improvement | F81: Streamlined core processes and management of service provisioning of frontline and other office deliverables to ensure ease of transations and/or digitalization/digitization | J81: Within the rating period | K81: 0.05 | L81: Quality | M81: Improvements/reduction on all of the service standards 1. no. of documentary requirements 2. total processing time 3. transaction cost 4. client steps/agency action steps 5. no. of signatories | N81: Improvements/reduction on 4 service standards 1. no. of documentary requirements 2. total processing time 3. transaction cost 4. client steps/agency action steps 5. no. of signatories | O81: Improvements/reduction on 2-3 service standards 1. no. of documentary requirements 2. total processing time 3. transaction cost 4. client steps/agency action steps 5. no. of signatories | P81: Improvements/reduction on 1 service standards 1. no. of documentary requirements 2. total processing time 3. transaction cost 4. client steps/agency action steps 5. no. of signatories | Q81: No change in no. of documentary requirements, total processing time, transaction cost, process steps, signatories | U81: =AVERAGE(T81:T83) -> #DIV/0! | V81: =U81*K81 -> #DIV/0!
L82: Efficiency | M82: Streamlined and/or digitized all office core processes identified in the QMS planning documents | N82: Streamlined and/or digitized 76-99% of the office core processes identified in the QMS planning documents | O82: Streamlined and/or digitized 51-75% of the office core processes identified in the QMS planning documents | P82: Streamlined and/or digitized 26-50% of the office core processes identified in the QMS planning documents | Q82: Streamlined and/or digitized 0-25% of the office core processes identified in the QMS planning documents
L83: Timeliness
B84: Client Satisfaction | F84: Achieved 100% resolution and compliance rate to #8888 and CCB complaints within the prescribed processing time (simple - 3 days; complex - 7 days; highly technical - 20 days) with at least Satisfactory overall average result on the Client Satisfaction Measurement | J84: Within the rating period | K84: 0.05 | L84: Quality | M84: 95.0% - 100% (Outstanding) overall average on the results of the Client Satisfaction Measurement (CSM) | N84: 90.9% - 94.9% (Very Satisfactory) overall average on the results of the CSM | O84: 80.0% - 89.9% (Satisfactory) overall average on the results of the CSM | P84: 60.0% - 79.9% (Fair) overall average on the results of the CSM | Q84: Below 60.0% (Poor) overall average on the results of the CSM | U84: =AVERAGE(T84:T86) -> #DIV/0! | V84: =U84*K84 -> #DIV/0!
L85: Efficiency | M85: 100% resolution and compliance rate to #8888 and CCB complaints | N85: At least 80% resolution and compliance rate to #8888 and CCB complaints | O85: At least 50% resolution and compliance rate to #8888 and CCB complaints | P85: At least 1% resolution and compliance rate to #8888 and CCB complaints | Q85: 0% resolution and compliance rate to #8888 and CCB complaints
L86: Timeliness | M86: Complaints acted upon and closed within prescribed processing time (simple - 3 days; complex - 7 days; highly technical - 20 days) | O86: Complaints are acted upon and closed with documented delays based on the prescribed processing time (simple - 3 days; complex - 7 days; highly technical - 20 days) | Q86: No complaint acted upon and resolved
B105: Part I-C Total Score | V105: =SUM(V78:V86) -> #DIV/0!
D112: RATEE | I112: RATER | N112: APPROVING AUTHORITY

Sheet PART I (CY 2025&SY2025-2026)
A2: OFFICE PERFORMANCE COMMITMENT AND REVIEW FORM (OPCRF) ver.Feb2025
A4: Name of Employee: | E4: MC WELSON C. SOLOMON | M4: Name of Rater: | N4: ROGER Z. ROCHAR, PhD
A5: Position/Designation: | E5: HEAD TEACHER III | M5: Position: | N5: OIC-ASDS
A6: Review Period: | E6: June 2025-July 2026 | M6: Approving Authority: | N6: PORTIA MISSION MALLORCA, PhD CESO V
A7: Division: | E7: City Schools Division of Victorias | M7: Date of Rating:
A8: Division Statement of Purpose: | E8: To improve the learning outcomes of the schools in SDO Victorias City
A10: PART I-A: COMMITMENT TO ORGANIZATIONAL OUTCOMES (60%) Part I-A. Commitment to Organizational Outcomes shall capture office commitments, performance, and accomplishments based on office mandates and KRAs as reflected in the official issuance on the Compendium of Office Functions. This part shall capture the contributions of the office directly targeting the Organizational Outcomes indicated in the General Appropriation Act (GAA) Programs/Subprograms, Basic Education Development Plan (BEDP) Pillars, Current Administration Agenda, and other national level commitments that are aligned with and relevant to the office KRAs. Clear attribution shall be made to ensure such alignment.
A12: TO BE ACCOMPLISHED DURING PLANNING | R12: TO BE FILLED DURING EVALUATION
A13: Organizational Outcomes Alignment | E13: Objectives (based on Office Functions) | G13: Timeline | H13: Weight Allocation | I13: Performance Targets (Target Outcome/ Ouput of the Bureau/ Center/Service/ Division aligned with the Outcome/Output Indicators in the Organizational Outcomes) | K13: Performance Measure (Quality, Efficiency, Timeliness) | L13: Rating Scale | Q13: Means of Verification (MOVs) | R13: Actual Accomplishments | S13: RATING (Q,E,T) | T13: AVERAGE (QET) | U13: WEIGHTED AVERAGE
A14: Key Result Areas (KRA) (Based on Office Mandate and Functions) | B14: Organizational Outcome Attribution (Refer to the GAA Programs/Subprogram and BEDP Pillars) | I14: Value (numerical, statistical, trend) | J14: Description (expected outcome/ output/service) | L14: 5 (Outstanding) | M14: 4 (Very Satisfactory) | N14: 3 (Satisfactory) | O14: 2 (Unsatisfactory) | P14: 1 (Poor)
B15: GAA Programs/ Subprograms | C15: BEDP Pillars | D15: Current Administration Agenda
A16: KRA 1: Curriculum and Teaching | B16: *Education Policy Development Program | C16: Quality | D16: High Quality of Education | E16: 1. Accounted for learning outcomes of school vis-a-vis goals and targets (Reduced Frustration Level Learners, Reduce Non-Numerates) ----------------------- 1.1. Achieved the targeted percentage of learners who are Grade Level Ready measured by CRLA | G16: June 2025-March 2026 | H16: 0.04 | I16: *based on CRLA EOSY 2024-2025 Baseline Data: 56.92 | J16: 100% of the targeted percentage (%) increase of Grade Level Ready learners measured by CRLA achieved | K16: Quality | L16: Exceeded 100% of the target in the percentage increase of Grade Level Ready learners based on CRLA, with only 1–2 lapses. | M16: Achieved 100% of the target in the percentage increase of Grade Level Ready learners based on CRLA, with only 3–4 lapses. | N16: Achieved 80%–99.9% of the target in the percentage increase of Grade Level Ready learners based on CRLA, with 5–6 lapses. | O16: Achieved 60%–79.9% of the target in the percentage increase of Grade Level Ready learners based on CRLA, with 7–8 lapses. | P16: Achieved below 60% of the target in the percentage increase of Grade Level Ready learners based on CRLA, with 9 or more lapses. | Q16: 1. CRLA Result (BOSY,EOSY)sheet per grade level 2. Consolidated CRLA school report 3. Comparative Analysis vs. target | S16: 5 | T16: =AVERAGE(S16:S21) -> 5 | U16: =T16*SUM(H16:H21) -> 0.2
K20: Efficiency | L20: Submitted the CRLA results complete, accurate, and fully supported by all required MOVs, with no deficiencies requiring resubmission. | M20: Submitted the CRLA results complete and supported by at least 4 required MOVs, with minimal deficiencies. | N20: Submitted the CRLA results supported by at least 3 required MOVs, with manageable deficiencies. | O20: Submitted the CRLA results supported by at least 2 required MOVs, with significant deficiencies. | P20: Submitted the CRLA results supported by only 1 or none of the required MOVs, with substantial deficiencies. | S20: 5
K21: Timeliness | L21: Submitted on or before the prescribed due date, with complete requirements ready for validation. | M21: Submitted 1–2 working days after the prescribed due date. | N21: Submitted 3–4 working days after the prescribed due date. | O21: Submitted 5–6 working days after the prescribed due date. | P21: Submitted 7 or more working days after the prescribed due date. | S21: 5
E22: 1.2. Achieved 50% of learners at Independent Level in Phil-IRI Filipino Results | H22: 0.03 | K22: Quality | L22: Achieved 50% and above of learners at Independent Level in Phil-IRI Filipino Results. | M22: Achieved 40-50% of learners at Independent Level in Phil-IRI Filipino Results. | N22: Achieved 30-40% of learners at Independent Level in Phil-IRI Filipino Results. | O22: Achieved 20-30% of learners at Independent Level in Phil-IRI Filipino Results. | P22: Achieved 20% and below of learners at Independent Level in Phil-IRI Filipino Results. | Q22: 1. Phil-IRI Filipino Consolidated BOSY Results 2.Phil-IRI Filipino Consolidated EOSY Results 3. Phil-IRI Filipino Grade Level BOSY Results 4. Phil-IRI Filipino Grade Level EOSY Results | S22: 3 | T22: =AVERAGE(S22:S24) -> 4.3333333 | U22: =T22*SUM(H22:H24) -> 0.13
K23: Efficiency | L23: Submitted Phil-IRI Filipino results and supported by all of the MOVs | M23: Submitted Phil-IRI Filipino results and supported by any 4 of the MOVs | N23: Submitted Phil-IRI Filipino results and supported by any 3 of the MOV | O23: Submitted Phil-IRI Filipino results and supported by any 2 of the MOV | P23: Submitted Phil-IRI Filipino results and supported by any 1 of the MOVs | S23: 5
K24: Timeliness | L24: Submitted on or before due date | M24: Submitted 1–2 days working days after due date | N24: Submitted 3–4 days working days after due date | O24: Submitted 5–6 days working days after due date | P24: Submitted 7–8 days working days after due date | S24: 5
E25: 1.3. Achieved 50% of learners at Independent Level in Phil-IRI English Results | H25: 0.03 | K25: Quality | L25: Achieved 50% and above of learners at Independent Level in Phil-IRI English Results. | M25: Achieved 40-50% of learners at Independent Level in Phil-IRI English Results. | N25: Achieved 30-40% of learners at Independent Level in Phil-IRI English Results. | O25: Achieved 20-30% of learners at Independent Level in Phil-IRI English Results. | P25: Achieved 20% and below of learners at Independent Level in Phil-IRI English Results. | Q25: 1. Phil-IRI English Consolidated BOSY Results 2. Phil-IRI English Consolidated EOSY Results 3. Phil-IRI English Grade Level BOSY Results 4. Phil-IRI English Grade Level EOSY Results | S25: 3 | T25: =AVERAGE(S25:S27) -> 4.3333333 | U25: =T25*SUM(H25:H27) -> 0.13
K26: Efficiency | L26: Submitted Phil-IRI English results and supported by all of the MOVs | M26: Submitted Phil-IRI English results and supported by any 4 of the MOVs | N26: Submitted Phil-IRI English results and supported by any 3 of the MOV | O26: Submitted Phil-IRI English results and supported by any 2 of the MOV | P26: Submitted Phil-IRI English results and supported by any 1 of the MOVs | S26: 5
K27: Timeliness | L27: Submitted on or before due date | M27: Submitted 1–2 days working days after due date | N27: Submitted 3–4 days working days after due date | O27: Submitted 5–6 days working days after due date | P27: Submitted 7–8 days working days after due date | S27: 5
E28: 1.4. Achieved 50% of learners at Proficient and Highly Proficient Level in RMA Results | H28: 0.02 | K28: Quality | L28: Achieved 50% and above of learners at Proficient and Highly Proficient Level in RMA Results | M28: Achieved 40-50% of learners at Proficient and Highly Proficient Level in RMA Results | N28: Achieved 30-40% of learners at Proficient and Highly Proficient Level in RMA Results | O28: Achieved 20-30% and of learners at Proficient and Highly Proficient Level in RMA Results | P28: Achieved 20% and below of learners at Proficient and Highly Proficient Level in RMA Results | Q28: 1. RMA Consolidated BOSY Results 2. RMA Consolidated EOSY Results 3. RMA Grade Level BOSY Results 4. RMA Grade Level EOSY Results | S28: 3 | T28: =AVERAGE(S28:S30) -> 4.3333333 | U28: =T28*SUM(H28:H30) -> 0.086666667
K29: Efficiency | L29: Submitted RMA results and supported by all of the MOVs | M29: Submitted RMA results and supported by any 4 of the MOVs | N29: Submitted RMA results and supported by any 3 of the MOV | O29: Submitted RMA results and supported by any 2 of the MOV | P29: Submitted RMA results and supported by any 1 of the MOVs | S29: 5
K30: Timeliness | L30: Submitted on or before due date | M30: Submitted 1–2 days working days after due date | N30: Submitted 3–4 days working days after due date | O30: Submitted 5–6 days working days after due date | P30: Submitted 7–8 days working days after due date | S30: 5
B31: Education Policy Development Program | E31: Prepared teachers and class program aligned with teachers area of specialization/expertise. | G31: Last Week of June 2025 | H31: 0.03 | I31: 1 | J31: Prepared teachers and class program aligned with teachers of specialization/expertise. | K31: Quality | L31: Prepared teachers and class program with 90-100% of the teachers aligned with their area of specialization/ expertise | M31: Prepared teachers and class program with 70-89% of the teachers aligned with their area of specialization/ expertise | N31: Prepared teachers and class program with 50-69% of the teachers aligned with their area of specialization/ expertise | O31: Prepared teachers and class program with 20-49% of the teachers aligned with their area of specialization/ expertise | P31: Prepared teachers and class program with 0-19% of the teachers aligned with their area of specialization/ expertise | Q31: 1. Certificate of Related Trainings 2. SF7 3. Approved Class and Teachers Program | S31: 5 | T31: =AVERAGE(S31:S33) -> 5 | U31: =T31*H31 -> 0.15
K32: Efficiency | L32: Teachers and class program submitted and approved 2 weeks before the start of classes | M32: Teachers and class program submitted with 3-5 corrections/ revisions. | N32: Teachers and class program submitted with 6-8 corrections/ revisions. | O32: Teachers and class program submitted with 9-11 corrections/ revisions. | P32: Teachers and class program submitted with 12 and more corrections/ revisions. | S32: 5
K33: Timeliness | L33: Teachers and class program submitted and approved 2 weeks before the start of classes | M33: Teachers and class program submitted and approved 1 week before the start of classes | N33: Teachers and class program submitted and approved on the start of classes | O33: Teachers and class program submitted and approved 1 week after the start of classes | P33: Teachers and class program submitted and approved 2 weeks after the start of classes | S33: 5
B34: *Education Policy Development Program *Education Human Resource Development Program | C34: Quality | D34: *High Quality of Education *High Performing Teacher | E34: 2. Performed Instructional Supervision | G34: June 2025-March 2026 | H34: 0.04 | I34: 1 | J34: Teachers Observation | K34: Quality | L34: 100% of planned instructional supervision reflected in the ISEAP is performed. | M34: 91-99% of planned instructional supervision reflected in the ISEAP is performed. | N34: 81-90% of planned instructional supervision reflected in the ISEAP is performed. | O34: 71-80% of planned instructional supervision reflected in the ISEAP is performed. | P34: 70% and below of planned instructional supervision reflected in the ISEAP is performed. | Q34: 1. ISEAP 2. ISEAR 3. COT 4. Observation Notes/ STAR Notes | S34: 3 | T34: =AVERAGE(S34:S36) -> 3 | U34: =T34*H34 -> 0.12
K35: Efficiency | L35: Submitted ISEAP Report and supported by all of the MOVs | M35: Submitted ISEAP Report and supported by any 4 of the MOVs | N35: Submitted ISEAP Report and supported by any 3 of the MOVs | O35: Submitted ISEAP Report and supported by any 2 of the MOVs | P35: Submitted ISEAP Report and supported by any 1 of the MOVs | S35: 3
K36: Timeliness | L36: Submitted a week before due date | M36: Submitted 1–2 days working days after due date | N36: Submitted 3–4 days working days after due date | O36: Submitted 5–6 days working days after due date | P36: Submitted 7–8 days working days after due date | S36: 3
B37: *Education Policy Development Program *Inclusive Education Program | D37: *Efficient and Supportive Governance Structure | E37: 3. Achieved target learner enrolled in Kindergarten | G37: June-July 2025 | H37: 0.04 | I37: 0.18 | J37: Learners enrolled in Kindergarten | K37: Quality | L37: 9% and above increase in enrollment | M37: 7-8% increase in enrollment | N37: 5-6% increase in enrollment | O37: 3-4% increase in enrollment | P37: 1-2% increase in enrollment | Q37: 1. SF1 2. SF4 | S37: 3 | T37: =AVERAGE(S37:S39) -> 3 | U37: =T37*H37 -> 0.12
K38: Efficiency | L38: Increased 9 and above learners enrolled over the previous year | M38: Increased 7-8 learners enrolled over the previous year | N38: Increased 5-6 learners enrolled over the previous year | O38: Increased 3-4 learners enrolled over the previous year | P38: Increased 1-2 learners enrolled over the previous year | S38: 3
K39: Timeliness | L39: Enrolled on-time | M39: Enrolled 1 day after the scheduled date | N39: Enrolled 2 days after the scheduled date | O39: Enrolled 3 days after the scheduled date | P39: Enrolled 4 days and beyond after the scheduled date | S39: 3
A40: KRA 2: Learning Environment | B40: *Basic Education Input Program | C40: Enabling Mechanism/Access | D40: Learners physical and Mental well-being protected | E40: Implemented and promoted Safe and Child friendly learning and school environment for learners. | G40: January – December 2026 | H40: 0.04 | I40: 1 | J40: PAPS on Learning Environment in WFP were accomplished | K40: Quality | L40: 91% and above of the PAPS on Learning Environment in WFP were accomplished | M40: 81-90% of the PAPS on Learning Environment in WFP were accomplished | N40: 71-80% of the PAPS on Learning Environment in WFP were accomplished | O40: 61-70% of the PAPS on Learning Environment in WFP were accomplished | P40: 60% and below of the PAPS on Learning Environment in WFP were accomplished | Q40: Approved Program of Works WFP Pictures (before and after repair) | S40: 5 | T40: =AVERAGE(S40:S42) -> 5 | U40: =T40*H40 -> 0.2
K41: Efficiency | L41: 91% and above compliance with the approved Program of Works | M41: 81-90% compliance with the approved Program of Works | N41: 71-80% compliance with the approved Program of Works | O41: 61-70% compliance with the approved Program of Works | P41: 60% and below compliance with the approved Program of Works | S41: 5
K42: Timeliness | L42: Accomplished on time based on the target date | M42: Accomplished 15 days after the target date | N42: Accomplished 30 days after the target date | O42: Accomplished 45 days after the target date | P42: Accomplished 60 days after the target date | S42: 5
E43: Provided safe and child-friendly learning and school environment through the implementation of the Child Protection Policy | G43: June 2025-March 2026 | H43: 0.03 | I43: 1 | J43: Implemented the Child Protection Policy of the school | K43: Quality | L43: 91-100% resolution of cases in the CPC/Zero CPC case | M43: 86-90% resolution of cases in the CPC | N43: 81-85% resolution of cases in the CPC; | O43: 76-80% resolution of cases in the CPC | P43: 71-75% resolution of cases in the CPC | Q43: List of CPC Members Minutes of the Meeting CPC Intake Sheet Accomplishment Report | S43: 5 | T43: =AVERAGE(S43:S45) -> 5 | U43: =T43*H43 -> 0.15
K44: Efficiency | L44: All MOVs are present | M44: 3 MOVs are present | N44: 2 MOVs are present | O44: 1 MOV is present | P44: No MOV | S44: 5
K45: Timeliness | L45: The was implemented as scheduled | M45: The program was implemented 1 month after the scheduled date | N45: The program was implemented 2 months after the scheduled date | O45: The program was implemented 3 months after the scheduled date | P45: The program was implemented 4 months after the scheduled date | S45: 5
B46: Education Policy Development Program | E46: Increased the participation of learners in school activities( Intramural, Galaw Pilipinas, Nestle Wellness, Boy Scout, Girl Scout, SELG, SSG) | G46: June 2025-March 2026 | H46: 0.03 | I46: 1 | J46: Participated in school activities | K46: Quality | L46: 90%-100% learners’ participation in school activities | M46: 80%-89% learners’ participation in school activities | N46: 70%-79% learners’ participation in school activities | O46: 60%-69% learners’ participation in school activities | P46: 50%-59% learners’ participation in school activities | Q46: School Calendar of Activities Pictures (Documentation) Attendance Sheet | S46: 5 | T46: =AVERAGE(S46:S48) -> 3.6666667 | U46: =T46*H46 -> 0.11
K47: Efficiency | L47: 90%-100% learners participated actively in school activities | M47: 80%-89% learners participated actively in school activities | N47: 70%-79% learners participated actively in school activities | O47: 60%-69% learners participated actively in school activities | P47: 50%-59% learners participated actively in school activities | S47: 3
K48: Timeliness | L48: All school activities done without delay and on scheduled date | M48: 2-3 days delay after the scheduled date | N48: 4-5 days delay after the scheduled date | O48: 6-7 days delay after the scheduled date | P48: 8-10 days delay after the scheduled date | S48: 3
A49: KRA 3: Leadership | B49: Education Policy Development Program | C49: Enabling Mechanisms: Governance and Management | D49: *Efficient and Supportive Governance Structures | E49: Ensured implementation of SIP and WFP | G49: Whole year-round | H49: 0.03 | I49: 100 | J49: Number of DepEd policies and issuances implemented | K49: Quality | L49: 90-100% of the items of SIP and WFP were implemented | M49: 80-89% of the policies and issuances implemented/disseminated to 90% of teachers after a week after its release. | N49: 70-79 % of the policies and issuances implemented/disseminated to 80% of teachers after two weeks after its release. | O49: 60-69% of the policies and issuances implemented/disseminated to 70% of teachers three weeks after its release. | P49: 50% and below of the policies and issuances implemented/disseminated to 60% and below of teachers four weeks after its release. | Q49: 1. Division Issuances and Policies 2. Minutes of the Meeting 3. Attendance of the Participants 4. Supervisory Plan | S49: 5 | T49: =AVERAGE(S49:S51) -> 5 | U49: =T49*H49 -> 0.15
K50: Efficiency | L50: Policies and issuances implemented to 100% of teachers with 0-1 misinterpretation | M50: Policies and issuances implemented 90% of teachers with 2-3 misinterpretation | N50: Policies and issuances implemented 80% of teachers with 4-5 misinterpretation | O50: Policies and issuances implemented 70% of teachers with 6-7 misinterpretation | P50: Policies and issuances implemented 50% and below of teachers with 8 and above misinterpretation | S50: 5
K51: Timeliness | L51: Implemented within the targeted time | M51: Implemented 1-2 days after the targeted time | N51: Implemented 3-4 days after the targeted time | O51: Implemented 5-6 days after the targeted time | P51: Implemented 7 and more days after the targeted time | S51: 5
D52: Empowered and employable Filipinos | E52: Organized functional school clubs and organization | G52: Whole year-round | H52: 0.03 | I52: 0.05 | J52: Number of functional school clubs and organization organized | K52: Quality | L52: 5 clubs and organizations organized and functional. | M52: 4 clubs and organizations organized and functional. | N52: 3 clubs and organizations organized and functional. | O52: 2 clubs and organizations organized and functional. | P52: 1 clubs and organizations organized and functional. | Q52: 1. List of Officers of Clubs and organizations 2. Constitution and By Laws 3. Annual Plan 4. Minutes of the Meeting 5. Accomplishment Report | S52: 3 | T52: =AVERAGE(S52:S54) -> 3.6666667 | U52: =T52*H52 -> 0.11
K53: Efficiency | L53: Submitted all required MOVs of organized and functional clubs and organizations | M53: Submitted 4 required MOVs of organized and functional clubs and organizations | N53: Submitted 3 required MOVs of organized and functional clubs and organizations | O53: Submitted 2 required MOVs of organized and functional clubs and organizations | P53: Submitted 1 required MOVs of organized and functional clubs and organizations | S53: 3
K54: Timeliness | L54: Organized and functional within the targeted time | M54: Organized and functional 1-2 days after the targeted time | N54: Organized and functional 3-4 days after the targeted time | O54: Organized and functional 5-6 days after the targeted time | P54: Organized and functional 7 and more days after the targeted time | S54: 5
D55: *Efficient and Supportive Governance Structures | E55: Submitted required reports and documents | G55: Whole year-round | H55: 0.04 | I55: 1 | J55: Percentage of submitted required reports | K55: Quality | L55: 100% of required reports and documents submitted | M55: 90-99% of required reports and documents submitted | N55: 80-89% of required reports and documents submitted | O55: 70-79% of required reports and documents submitted | P55: 69 and below of required reports and documents submitted | Q55: 1. School Forms 2. NSBI Report 3. SBFP 4. EBEIS 5. DRRM 6. Adopt a School 7. Brigada Eskwela Reports 8. MPS/Learning Outcomes 9. Others (as required) | S55: 4 | T55: =AVERAGE(S55:S57) -> 4 | U55: =T55*H55 -> 0.16
K56: Efficiency | L56: All MOVs submitted with 0-2 revisions. | M56: All MOVs submitted with 3-4 revisions. | N56: All MOVs submitted with 5-6 revisions. | O56: All MOVs submitted with 7-8 revisions. | P56: All MOVs submitted with 9 and above revisions. | S56: 4
K57: Timeliness | L57: Submitted within the due date | M57: Submitted 1-2 days after due date | N57: Submitted 3-4 days after due date | O57: Submitted 5-6 days after due date | P57: Submitted 7 and more days after due date | S57: 4
A58: KRA 4: Governance and Accountability | B58: Support to school and learner program | C58: Enabling mechanism: Governance and Management | D58: Efficient learning delivery in all its forms | E58: Crafted WFP, APP, PPMP and Annual Budget Allocation | G58: 45962 | H58: 0.04 | I58: 4 | J58: WFP, APP, PPMP and Annual Budget Allocation crafted | K58: Quality | L58: Crafted all plans with the following 4 qualities: correct format, aligned with DepEd order no.8, s. of 2019, addresses school priority needs based on SIP, and participated by the school planning team. | M58: Crafted all plans with any 3 of the stated qualities | N58: Crafted all plans with any 2 of the stated qualities | O58: Crafted all plans with any 1 of the stated qualities | P58: Crafted all plans with 0 of the stated qualities | Q58: 1. Approved WFP 2. Approved APP 3. Approved PPMP 4. Approved Annual Budget Allocation | S58: 5 | T58: =AVERAGE(S58:S60) -> 5 | U58: =T58*H58 -> 0.2
K59: Efficiency | L59: Crafted all plans with 0-2 corrections/ revisions | M59: Crafted plans with 3-4 corrections/ revisions | N59: Crafted all plans with 5-6 corrections/revisions | O59: Crafted all plans with 7-8 corrections/ revisions | P59: Crafted all plans with 9 and above corrections/ revisions | S59: 5
K60: Timeliness | L60: Crafted all plans and submitted on time | M60: Crafted all plans and submitted 1-3 days after | N60: Crafted all plans and submitted 4-6 days after | O60: Crafted all plans and submitted 7-8 days after | P60: Crafted all plans and submitted 9-10 days after | S60: 5
B61: Basic Education Inputs Program | E61: Conducted Inventory of School Facilities | G61: February-May 2026 | H61: 0.03 | I61: 1 | J61: School Facilities accounted for | K61: Quality | L61: 90-100% school facilities accounted | M61: 80%-89% school facilities accounted | N61: 70%-79% school facilities accounted | O61: 60%-69% school facilities accounted | P61: 50%-59% school facilities accounted | Q61: 1. NSBI Data gathering form 2. Signed NSBI Report 3. NSBI LIS-based Validation 4. Photos on the conduct of the inventory | S61: 4 | T61: =AVERAGE(S61:S63) -> 4.3333333 | U61: =T61*H61 -> 0.13
K62: Efficiency | L62: Conducted inventory with 0 correction upon validation | M62: Conducted inventory with 1-2 corrections upon validation | N62: Conducted inventory with 3-4 corrections upon validation | O62: Conducted inventory with 5-6 corrections upon validation | P62: Conducted inventory with 7 and above corrections upon validation | S62: 4
K63: Timeliness | L63: Submitted inventory report within the scheduled period | M63: Submitted inventory report 1week after the scheduled date. | N63: Submitted inventory report 2 weeks after the scheduled date | O63: Submitted inventory report 3 weeks after the scheduled date. | P63: Submitted inventory report 4 weeks after the scheduled date. | S63: 5
A64: KRA 5: Human Resource & Team Development | B64: Education Human Resource Development Program | C64: Quality | D64: *High Performing Teachers *High Quality of Education | E64: Provided opportunities for professional development and teachers through capacity building trainings and LAC sessions. | G64: June 2025 - March 2026 | H64: 0.02 | I64: 1 | J64: Teachers’ capacity building trainings and LAC sessions provided | K64: Quality | L64: 100% of teachers attended trainings and LAC Sessions | M64: 90–99% attendance; moderate application of training content | N64: 80–89% attendance; some evidence of application | O64: 60–79% attendance; little to no visible improvement | P64: Below 60% attendance; no change in teaching practices | Q64: 1. Approved LAC PLAN/Training Matrix 2.Attendance Sheet 3.Minutes and Documentation 4.LAC Portfolio/Outputs/Reflection Journal 5. Certificate of Training/Completion | S64: 2 | T64: =AVERAGE(S64:S66) -> 2 | U64: =T64*H64 -> 0.04
K65: Efficiency | L65: Conducted Approved LAC Plan with all MOVs present | M65: Conducted Approved LAC Plan 4 MOVs present | N65: Conducted Approved LAC Plan 3 MOVs present | O65: Conducted Approved LAC Plan 2 MOVs present | P65: Conducted Approved LAC Plan 1 MOV present | S65: 2
K66: Timeliness | L66: Submitted Approved LAC Plan on time | M66: Submitted Approved LAC Plan 1-2 days after due date | N66: Submitted Approved LAC Plan 3-4 days after due date | O66: Submitted Approved LAC Plan 5-6 reports after due date | P66: Submitted Approved LAC Plan 7 days and beyond after due date | S66: 2
E67: Implemented school PRAISE Plan and reward system to recognize and motivate teachers exemplary performance and/or continued support. | G67: June 2025 - March 2026 | H67: 0.01 | I67: 1 | J67: School PRAISE Plan and recognition implemented | K67: Quality | L67: The PRAISE plan recognizes a wide range of personnel and stakeholders; awards are aligned with DepEd guidelines; criteria are clear and strictly followed; recognition is meaningful and contributes to motivation and morale. | M67: The PRAISE plan recognizes most deserving individuals; criteria are followed with minor lapses; recognition activities are conducted formally and positively impact school climate. | N67: The PRAISE plan is implemented but lacks clarity in criteria or consistency in selection | O67: The PRAISE plan is poorly implemented; recognition is limited to a few individuals without clear justification; little to no impact on staff motivation. | P67: No meaningful implementation of PRAISE plan; recognition activities are absent or irrelevant | Q67: 1.School PRAISE Plan 2.Certificate of Recognition 3.Certificate of Participation 4.List of Awards given and the recipient 5.School Memorandum re School PRAISE Committee | S67: 2 | T67: =AVERAGE(S67:S69) -> 2 | U67: =T67*H67 -> 0.02
K68: Efficiency | L68: Implemented the school PRAISE plan with 5 MOVs evident | M68: Implemented the school PRAISE plan with 4 MOVs evident | N68: Implemented the school PRAISE plan with 3 MOVs evident | O68: Implemented the school PRAISE plan with 2 MOVs evident | P68: Implemented the school PRAISE plan with 1 MOV evident | S68: 2
K69: Timeliness | L69: Awards given as scheduled | M69: Awards given 2-3 days after the scheduled date | N69: Awards given 4-5 days after the scheduled date | O69: Awards given 6-7 days after the scheduled date | P69: Awards given 8 days and beyond the scheduled date | S69: 2
B70: *Education Human Resource Development Program *Education Policy Development Program | D70: *High Performing Teachers *Efficient and Supportive Governance Structure | E70: Implemented the following programs and activities for teachers’ welfare. a.GAD b.Wellness Program c.Magna Carta for Public School Teachers d.School Grievance Committee e.Spirituality in the Workplace | G70: June 2025 - March 2026 | H70: 0.02 | I70: 5 | J70: KR | K70: Quality | L70: All 5 programs/activities implemented with evidence of high engagement and clear alignment with teacher welfare objectives | M70: 4 programs implemented and aligned with teacher welfare needs | N70: 3 programs implemented; documentation present, but limited in scope or reach | O70: Only 2 programs implemented with minimal impact or participation | P70: Only 1 program partially implemented or not fully aligned with teacher welfare goals | Q70: Activity proposals and accomplishment reports (per welfare program) Attendance sheets for TIP, wellness, and GAD sessions Documentation (photos/videos) of program implementation Grievance Committee Reports and orientation records Teacher feedback/evaluation results Copy of Magna Carta-related programs (orientation/training documents) Minutes of GAD or wellness meetings and trainings Certificates of participation issued to teachers Monitoring and Evaluation Reports with ratings or reflections | S70: 3 | T70: =AVERAGE(S70:S72) -> 3 | U70: =T70*H70 -> 0.06
K71: Efficiency | L71: All programs conducted with optimal use of resources, achieved targets without delays or complaints | M71: Programs implemented with minor resource issues, but targets still met | N71: Moderate inefficiencies affecting 1–2 programs | O71: Major inefficiencies in multiple programs; low participation or disrupted activities | P71: Programs implemented haphazardly with minimal attendance or high cost | S71: 3
K72: Timeliness | L72: All programs implemented within the planned schedule (August 2024 – April 2025) | M72: 1 program was delayed not more than 1 week | N72: 2 programs delayed within 2 weeks of the original schedule | O72: More than 2 programs experienced delays beyond 2 weeks | P72: Most or all programs not completed within the school year | S72: 3
A73: KRA: 6 Finance and Resource Manage and Mobilzation | B73: Support to Schools and Learners Program | C73: Resilience and Well-Being | D73: Learners Physical and Mental well-being Potected | E73: Increase stakeholder’s participation to support the implementation of school-based feeding program. | G73: June 2025 – March 2026 | H73: 0.02 | I73: 0.05 | J73: Increase of stakeholders’ participation | K73: Quality | L73: 5 Percent or more increased in stakeholders participation | M73: 4 Percent increased in stakeholders participation | N73: 3 Percent increased in stakeholders participation | O73: 2 Percent increased in stakeholders participation | P73: 1 Percent increased in stakeholders participation | Q73: DPDS Acknowledgement letter/Deed of Donation Photo Documentation of Innovation Implementation | R73: 1. Adopt a School Program successfully generated over Php10,000.00 worth of materials 2. Improve learners participation 3. Improved learners comprehension | S73: 4 | T73: =AVERAGE(S73:S75) -> 4 | U73: =T73*H73 -> 0.08
K74: Efficiency | L74: Stakeholders participation is supported by Accomplishment Report Attendance Sheet Deed of Donation Memorandum of Agreement Baseline and Endline Nutritional Status Report of Learners | M74: Stakeholders participation is supported by Accomplishment Report, attendance sheets, deed of donations, and MOA, | N74: Stakeholders participation is supported by Accomplishment Report, attendance sheets, and deed of donations, | O74: Stakeholders participation is supported by Accomplishment Reportand attendance sheets | P74: Stakeholders participation is supported by Accomplishment Report | S74: 4
K75: Timeliness | L75: Materials donated are fully used by learners all across the quarter on time | S75: 4
D76: Efficient and Supportive Governace Structure | E76: Ensured the efficient, transparent and timely utilization and mobilization of program funds and donations. | G76: June 2025 – March 2026 | H76: 0.015 | I76: 1 | J76: Disbursed, utilized, liquidated, and reported financial utilization | K76: Quality | L76: 100 percent delivered, properly liquidated and submitted planned financial resource. | M76: 80 percent delivered, properly liquidated and submitted planned financial resource. | N76: 60 percent delivered, properly liquidated and submitted planned financial resource | O76: 40 percent delivered, properly liquidated and submitted planned financial resource | P76: 20 percent delivered, properly liquidated and submitted planned financial resource | Q76: DPDS Acknowledgement letter/Deed of Donation Photo Documentation of Innovation Implementation | R76: 1. Adopt a School Program successfully generated over Php10,000.00 worth of materials 2. Improve learners participation 3. Improved learners comprehension | S76: 4 | T76: =AVERAGE(S76:S78) -> 4 | U76: =T76*H76 -> 0.06
K77: Efficiency | L77: Disbursed, utilized, liquidated, and reported financial utilization on time | M77: Disbursed, utilized, liquidated, and reported financial utilization 1 day after the deadline | N77: Disbursed, utilized, liquidated, and reported financial utilization 7 days after the deadline | O77: Disbursed, utilized, liquidated, and reported financial utilization 15 days after the deadline | P77: Disbursed, utilized, liquidated, and reported financial utilization 30 days after the deadline | S77: 4
K78: Timeliness
D82: Learners Physical and Mental Well-being Protected | E82: Improved the nutritional status and overall well-being of learners | G82: June 2025 – March 2026 | H82: 0.015 | I82: 1 | J82: Beneficiaries improved nutritional status from school-based feeding program | K82: Quality | L82: 79/79 100% of the benefiaries improved their nutritional status and overall well-being of learners | M82: 75-78 (95-99%) learners improved their nutritional status and overall well-being. | N82: 67-74 ((85-94%) learners improved their nutritional status and overall well-being | O82: 56-66 (70-74%) learners improved their nutritional status and overall well-being | P82: Fewer than 56 learners (<70%) learners improved their nutritional status and overall well-being. | Q82: 1. DPDS 2. Acknowledgement Letter/Deed of Donation 3.Photo Documentation of Innovation Implementation | R82: 1. Adopt a School Program successfully generated over Php10,000.00 worth of materials 2. Improve learners participation 3. Improved learners comprehension | S82: 5 | T82: =AVERAGE(S82:S84) -> 5 | U82: =T82*H82 -> 0.075
K83: Efficiency | L83: Nutrituous Food packs were 100% fully utilized , given and distributed to all recipients | M83: Nutrituous Food packs were 90%-99% utilized , given and distributed to all recipients | N83: Nutrituous Food packs were 80%-89% utilized , given and distributed to all recipients | O83: Nutrituous Food packs were 50%-79% utilized , given and distributed to all recipients | P83: Nutrituous Food packs were 0%-49% utilized , given and distributed to all recipients | S83: 5
K84: Timeliness | L84: All feeding activities were implemented ahead of schedule with full compliance of report | M84: All feeding activities were implemented with minor delays without compromising learners needs base on program implementation plan | N84: All feeding activities were done with minor delays without compromising learners needs | O84: All feeding activities were delayed beyond acceptable timeline impacting services given to the learners | P84: All feeding activities were not conducted or extremely delayed resulting in non implementation of the program | S84: 5
Q85: Part I-A Total Score | U85: =SUM(U16:U84) -> 2.4816667
A87: PART I-B: INNOVATING AND INTERVENING ACCOMPLISHMENTS (20%) Part I-B. Innovating and Intervening Accomplishments shall capture the outcomes/outputs of the office that are enabling, supportive, and/or contributory to the achievement of the organizational commitments and KRAs in Part I-A. Accomplishments can be innovations, interventions, and enhancements on the processes, services, and/or outputs.
A88: TO BE FILLED IN DURING PLANNING | R88: TO BE FILLED DURING EVALUATION
A89: Key Result Areas (KRA) | E89: Objectives | G89: Timeline | H89: Weight Allocation | I89: Performance Targets (Target Outcome/Ouput of the Bureau/Center/Service/Division that are enabling, supportive, and/or contributory to the achievement of the organizational outcomes and KRAs (Part I-A)) | K89: Performance Measure (Quality, Efficiency, Timeliness) | L89: RATING SCALE | Q89: Means of Verification (MOVs) | R89: Actual Results/ Accomplishments | S89: RATING (Q,E,T) | T89: AVERAGE (QET) | U89: WEIGHTED AVERAGE | AE89: op
I90: Value (numerical, statistical, trend) | J90: Description (expected outcome/ output/service) | L90: 5 (Outstanding) | M90: 4 (Very Satisfactory) | N90: 3 (Satisfactory) | O90: 2 (Unsatisfactory) | P90: 1 (Poor)
A91: KRA 1: Curriculum and Teaching | E91: Implemented/conducted and maintained innovations and intervention of National/Division/School-led curricular programs in the school following guidelines and mechanics: ARAL Project SUPER+ Project 5K STAANG Project SANYOG Project DOREMI Project Rewinds Project Bridge 2.0 Cha-Ching | G91: June 2025 – March 2026 | H91: 0.05 | I91: 6 | J91: Curricular programs adopted and maintained | K91: Quality | L91: 7 curricular innovations from the CID adopted and maintained | M91: 6 curricular innovations from the CID adopted and maintained | N91: 5 curricular innovations from the CID adopted and maintained | O91: 3-4 curricular innovations from the CID adopted and maintained | P91: 1-2 curricular innovations from the CID adopted and maintained | Q91: 1. School Memorandum on Adoption of all CID-led Innovations 2.End-of-the-year Report on Adoption of all CID-led Innovations 3. Monitoring and evaluation Report on Adoption of all CID-led Innovations 4. Success Stories of Innovation Adoption 5.Photo Documentation of Innovation Implementation | S91: 5 | T91: =AVERAGE(S91:S93) -> 5 | U91: =T91*H91 -> 0.25
K92: Efficiency | L92: curricular innovations adopted and maintained as supported by 5 MOVs | M92: curricular innovations adopted and maintained as supported by 4 MOVs | N92: curricular innovations adopted and maintained as supported by 3 MOVs | O92: curricular innovations adopted and maintained as supported by 2 MOVs | P92: curricular innovations adopted and maintained as supported by 1 MOV | S92: 5
K93: Timeliness | L93: Submitted adoption and implementation report a week before due date | M93: Submitted adoption and implementation report 1–2 days working days after due date | N93: Submitted adoption and implementation report 3–4 days working days after due date | O93: Submitted adoption and implementation report 5–6 days working days after due date | P93: Submitted 7–8 days working days after due date | S93: 5
A94: KRA 2: Learning Environment | E94: *Promoted a safe, clean and healthy learning environment by implementing the following Clean And Green program component 1. Waste Segregation 2. Project SANYOG 3. Edible Landscaping 4. Gulayan sa Paaralan *Provided safe and child-friendly learning and school environment through the implementation of the Child Protection Policy | G94: June 2025 – March 2026 | H94: 0.03 | I94: 1 | J94: Clean and Green program implemented | K94: Quality | L94: 5- 95% -100% implemented and sustained Clean and Green program | M94: 4- 90% - 94% implemented and sustained Clean and Green program | N94: 3- 85% - 89% implemented and sustained Clean and Green program | O94: 2- 80% - 84% implemented and sustained Clean and Green program | P94: 1- 75% - 79% implemented and sustained Clean and Green program | Q94: 1.School Memo 2.Minutes of the Meeting 3.M&E tool 4.Attendance Sheet 5.Quarterly Accomplishment Reports 6.Pictures | S94: 5 | T94: =AVERAGE(S94:S97) -> 5 | U94: =T94*H94 -> 0.15
K95: Efficiency | L95: 5- All MOVs are submitted | M95: 4- 4-5 MOVs are submitted | N95: 3- 3 MOVs are submitted | O95: 2- 2 MOVs are submitted | P95: 1- 1 MOV are submitted | S95: 5
K96: Timeliness | L96: (Clean and Green components will be implemented throughout the year) | S96: 5
S97: 5
A98: KRA 3: Leadership | E98: Adopted a school-coded scheme for school priority improvement areas using the SUG Analysis Red - High Priority Yellow - Medium Priority Green - Low Priority | G98: June 2025 – March 2026 | H98: 0.03 | I98: 1 | J98: School priority improvement areas coded | K98: Quality | L98: 95-100% of school priority improvement areas are accurately coded. | M98: 90-94% of school priority improvement areas are accurately coded. | N98: 85-89% of school priority improvement areas are accurately coded. | O98: 80-84% of school priority improvement areas are accurately coded. | P98: Below 80% of school priority improvement areas are accurately coded. | Q98: 1. List of Prioritized Improvement Atreas 2. Color-coded School Priority Improvement Areas 3. School Improvement Plan | S98: 5 | T98: =AVERAGE(S98:S100) -> 5 | U98: =T98*H98 -> 0.15
K99: Efficiency | L99: 3 MOVs are present and evident | N99: 2 MOVs are present and evident | P99: 1 MOV is present and evident | S99: 5
K100: Timeliness | S100: 5
A101: KRA 4: Governance and Accountability | E101: Created and Implemented Digitized School Dashboard for Personnel and Physical Resources | G101: 2nd week of July, 2025 | H101: 0.03 | I101: 1 | J101: Digitized Dashboard with 5 tabs | K101: Quality | L101: 1 dashboard with 5 tabs created and implemented: 1. Personnel Profile 2. Teaching Load 3. Building Inventory 4. Classroom Resources 5. Learning Resources | M101: 1 dashboard created and implemented with 4 tabs | N101: 1 dashboard created and implemented with 3 tabs | O101: 1 dashboard created and implemented with 2 tabs | P101: 1 dashboard created and implemented with 1 tab | Q101: 1. Screenshot of Dashboards with number of tabs. | S101: 5 | T101: =AVERAGE(S101:S103) -> 5 | U101: =T101*H101 -> 0.15
K102: Efficiency | L102: Updated 1 dashboard with 5 tabs | M102: Updated 1 dashboard with 4 tabs | N102: Updated 1 dashboard with 3 tabs | O102: Updated 1 dashboard with 2 tabs | P102: Updated 1 dashboard with 1 tab | S102: 5
K103: Timeliness | L103: Creates, implemented and maintained 2 weeks before the beginning of classes or as needed | M103: Creates, implemented and maintained 1 week before the beginning of classes or as needed | N103: Creates, implemented and maintained within the beginning of classes or as needed | O103: Creates, implemented and maintained 1 week after the beginning of classes or as needed | P103: Creates, implemented and maintained 2 weeks after the beginning of classes or as needed | S103: 5
A104: KRA 5: Human Resource and Team Development | E104: Encouraged school personnel to conduct 1 action research, basic research and/or innovation focusing on the impact of any of the following division-led projects: A. Project STA-ANG B. Project SUPER AND SUPER+ C. Project BRIDGE 2.0 D. Project 5K E. Project SANYOG F. Project Do-Re-Mi | G104: June 2025 – March 2026 | H104: 0.03 | I104: 1 | J104: Action/basic research and/or innovation conducted that focus on any of the following categories (Curriculum and Instruction Delivery , Policy, Planning, Research, & Governance, Learning Environment Improvement, Human Resource Development , ALS, SPED, & IPEd Programs) | K104: Quality | L104: One (1) approved action research, basic research, or innovation was successfully conducted and presented during a Learning Action Cell (LAC) session, meeting the following key indicators: a. Credibility – Demonstrated rigor, transparency, and consistency throughout the process. b. Contribution – Addressed relevant issues, introduced original ideas, and produced findings with potential for broader application. c. Communicability – Results were presented in a manner that is accessible, understandable, and usable by intended stakeholders. d. Conformity – Fully aligned with existing policies, adhered to ethical standards, and promoted sustainability. | M104: One (1) approved action research, basic research, or innovation was successfully conducted and met at least three (3) of the following indicators | N104: One (1) approved action research, basic research, or innovation was successfully conducted and met at least two (2) of the following indicators | O104: One (1) approved action research, basic research, or innovation was successfully conducted and demonstrated alignment with at least one (1) of the following indicator. | P104: One (1) approved action research, basic research, or innovation was conducted and maintained; however, it did not meet any of the established indicators. | Q104: a. Completed Action Research / Innovation Paper b. Approval Letter / Certification c. Photo Documentation d. Accomplishment Report e. Presentation Materials with LAC Session Minutes | S104: 5 | T104: =AVERAGE(S104) -> 5 | U104: =T104*H104 -> 0.15
K105: Efficiency | L105: One (1) approved action research, basic or innovation was conducted, maintained, and supported by the following Means of Verification (MOVs): a. Completed Action Research / Innovation Paper b. Approval Letter / Certification c. Photo Documentation d. Accomplishment Report e. Presentation Materials with LAC Session Minutes | M105: One (1) approved action research, basic research, or innovation was successfully conducted and maintained. Its implementation was duly supported by four (4) Means of Verification (MOVs), namely: a. Completed Action Research / Innovation Paper b. Approval Letter / Certification c. Photo Documentation d. d. Accomplishment Report | N105: One (1) approved action research, basic research, or innovation was successfully conducted and maintained. Its implementation was duly supported by three (3) Means of Verification (MOVs), namely: a. Completed Action Research / Innovation Paper b. Approval Letter / Certification c. Photo Documentation | O105: One (1) approved action research, basic research, or innovation was successfully conducted and maintained. Its implementation was duly supported by four (2) Means of Verification (MOVs), namely: a. Completed Action Research / Innovation Paper b. Approval Letter / Certification | P105: No approved action research, basic research, or innovation was developed or implemented. | S105: 5
K106: Timeliness | L106: An action research, basic research, or innovation was conducted as scheduled within the prescribed timeline, with the completed paper submitted 2–3 days ahead of the deadline. | M106: An action research, basic research, or innovation was conducted one week after the scheduled date, with the completed paper submitted on the deadline. | N106: An action research, basic research, or innovation was conducted one week after the scheduled date, with the completed paper submitted 2–3 days after the deadline. | O106: An action research, basic research, or innovation was conducted one week after the scheduled date, with the completed paper submitted 4–5 days after the deadline. | P106: The action research, basic research, or innovation was neither completed nor submitted. | S106: 5
A107: KRA 6: Finance and Resource Manage Mobilization | E107: To Implement Adopt a School Program, a whole year round stakeholders -driven learning support. | G107: June 2025 – March 2026 | H107: 0.03 | I107: 10 | J107: Adopt a School Program will generate Php10,000.00 or more worth of resources | K107: Quality | L107: 100% of materials mobilized through donations are relevant to support learning. | M107: 80–99% of materials mobilized through donations are relevant to support learning. | N107: 60–79% of materials mobilized through donations are relevant to support learning. | O107: 40–59% of materials mobilized through donations are relevant to support learning. | P107: Less than 40% of materials mobilized through donations are relevant to support learning. | Q107: DPDS Acknowledgement letter/Deed of Donation Photo Documentation of Innovation Implementation | R107: 1. Adopt a School Program successfully generated over Php10,000.00 worth of materials 2. Improve learners participation 3. Improved learners comprehension | S107: 5 | T107: =AVERAGE(S107:S109) -> 5 | U107: =T107*H107 -> 0.15
K108: Efficiency | L108: 100% of materials mobilized through donations are relevant to support learning. | M108: 80–99% of materials mobilized through donations are relevant to support learning. | N108: 60–79% of materials mobilized through donations are relevant to support learning. | O108: 40–59% of materials mobilized through donations are relevant to support learning. | P108: Less than 40% of materials mobilized through donations are relevant to support learning. | S108: 5
K109: Timeliness | L109: Materials donated are fully used by learners all across the quarter on time | M109: Materials donated are fully used by learners all across the quarter mostly on time | N109: Materials donated are fully used by learners all across the quarter partly on time | O109: Materials donated are fully used by learners all across the quarter were somewhat delayed | P109: Materials donated are used by learners all across the quarter delayed in implementation | S109: 5
A110: Part I-B Total Score | U110: =SUM(U91:U109) -> 1
A112: PART I-C: ORGANIZATIONAL EFFECTIVENESS (15%) Part I-C. Organizational Effectiveness shall capture accomplishments/outputs produced or attained on the aspects of Financial Stewardship, Process Improvement, and Client Satisfaction. It shall focus on the results achieved by the office that are aligned with the Performance-based Bonus (PBB) oversight requirements. | R112: PART I-C: ORGANIZATIONAL EFFECTIVENESS (15%) Part I-C. Organizational Effectiveness shall capture accomplishments/outputs produced or attained on the aspects of Financial Stewardship, Process Improvement, and Client Satisfaction. It shall focus on the results achieved by the office that are aligned with the Performance-based Bonus (PBB) oversight requirements.
...

Sheet PART II
A1: https://sites.google.com/d/1_1eBFZEbY7KEjZv2ky2awGZobqs4cVrR/p/1z3uHqg8VN3L7dAZ2S0aHfB10Az0DeJd4/edit
B2: DepEd OPCRF (ver.Feb2025), page 2 of 4
B3: PART II-A: LEADERSHIP COMPETENCIES (2.5%) Part II-A. Leadership Competencies shall capture competencies expected of heads of functional offices who hold managerial and executive/supervisory positions. The Leadership Competencies expected to be demonstrated include Leading People, People Performance Management, and People Development.
B4: Competencies | C4: Behavioural Indicators | G4: Remarks/ Observations | I4: RATING | J4: AVERAGE | L4: DepEd Competencies Scale
L5: Numerical Rating | M5: Adjectival Rating | N5: Definition
B6: Leading People | C6: 1. Uses basic persuasion techniques in a discussion or presentation e.g., staff mobilization, appeals to reason and/or emotions, uses data and examples, visual aids | I6: 4 | J6: =AVERAGE(I6:I10) -> 4.2 | L6: 5 | M6: Role Model | N6: Behavioral indicator is consistently exhibited and is worthy of emulation.
C7: 2. Persuades, convinces or influences others, in order to have a specific impact or effect. | I7: 4 | L7: 4 | M7: Consistently Demonstrated | N7: Behavioral indicator is constantly shown.
C8: 3. “Sets a good example”, is a credible and respected leader; and demonstrates desired behavior. | I8: 4 | L8: 3 | M8: Most of the Time Demonstrated | N8: Behavioral indicator is often shown.
C9: 4. Forwards personal, professional and work unit needs and interests in an issue. | I9: 4 | L9: 2 | M9: Sometimes Demonstrated | N9: Behavioral indicator is irregularly shown.
C10: 5. Assumes a pivotal role in promoting the development of an inspiring, relevant vision for the organization and influences others to share ownership of DepEd goals, in order to create an effective work environment. | I10: 5 | L10: 1 | M10: Rarely Demonstrated | N10: Behavioral indicator is seldom shown.
B11: People Performance Management | C11: 1. Makes specific changes in the performance management system or in own work methods to improve performance (e.g. does something better, faster, at lower cost, more efficiently; improves quality, customer satisfaction, morale, revenues). | I11: 5 | J11: =AVERAGE(I11:I15) -> 4.2
C12: 2. Sets performance standards and measures progress of employees based on office and department targets. | I12: 4
C13: 3. Provides feedback and technical assistance such as coaching for performance improvement and action planning. | I13: 5
C14: 4. States performance expectations clearly and checks understanding and commitment. | I14: 3
C15: 5. Performs all the stages of result-based performance management system supported by evidence and required documents/forms. | I15: 4
B16: People Development | C16: 1. Improves the skills and effectiveness of individuals through employing a range of development strategies. | I16: 5 | J16: =AVERAGE(I16:I20) -> 4.4
C17: 2. Facilitates workforce effectiveness through coaching and motivating/developing people within a work environment that promotes mutual trust and respect. | I17: 4
C18: 3. Conceptualizes and implements learning interventions to meet identified training needs. | I18: 5
C19: 4. Does long-term coaching or training by arranging appropriate and helpful assignments, formal training, or other experiences for the purpose of supporting a person’s learning and development. | I19: 4
C20: 5. Cultivates a learning environment by structuring interactive experiences such as looking for future opportunities that are in support of achieving individual career goals. | I20: 4
B21: Part II-A Total Score: Weighted Average (Average x 0.025) | J21: =AVERAGE(J6:J20)*0.025 -> 0.10666667
B22: PART II-B: CORE BEHAVIOURAL COMPETENCIES (2.5%) Part II-B. Core Behavioral Competencies shall capture competencies required from all DepEd personnel in all job groups within the organization, upholding the DepEd’s core values and the Code of Conduct and Ethical Standards for Public Officials and Employees pursuant to RA 6713. They represent the way individuals embody and live the values of the organization.
B23: Competencies | C23: Behavioural Indicators | G23: Remarks/ Observations | I23: RATING | J23: AVERAGE
B25: Self-Management | C25: 1. Sets personal goals and direction, needs and development. | I25: 4 | J25: =AVERAGE(I25:I29) -> 4.2
C26: 2. Understands personal actions and behavior that are clear and purposive and takes into account personal goals and values congruent to that of the organization | I26: 4
C27: 3. Displays emotional maturity and enthusiasm for and is challenged by higher goals | I27: 5
C28: 4. Prioritize work tasks and schedules (through Gantt charts, checklists, etc.) to achieve goals | I28: 4
C29: 5. Sets high quality, challenging, realistic goals for self and others. | I29: 4
B30: Professionalism and Ethics | C30: 1. Demonstrate the values and behavior enshrined in the Norms and Conduct and Ethical Standards for Public Officials and Employees (RA 6713). | I30: 4 | J30: =AVERAGE(I30:I34) -> 4.2
C31: 2. Practice ethical and professional behavior and conduct taking into account the impact of his/her actions and decisions. | I31: 4
C32: 3. Maintains a professional image: being trustworthy, regularity of attendance and punctuality, good grooming and communication. | I32: 4
C33: 4. Makes personal sacrifices to meet the organization’s needs. | I33: 5
C34: 5. Act with a sense of urgency and responsibility to meet the organization’s needs, improve system and help others improve their effectiveness. | I34: 4
B35: Results Focus | C35: 1. Achieves results with optimal use of time and resources mist of the time. | I35: 4 | J35: =AVERAGE(I35:I39) -> 4
C36: 2. Avoids rework, mistakes and wastage through effective work methods by placing organizational needs before personal needs. | I36: 4
C37: 3. Delivers error-free outputs most of the time by conforming to standard operating procedures correctly and consistently. Able to produce very satisfactory quality of work in terms of usefulness/acceptability and completeness with no supervision required. | I37: 4
C38: 4. Expresses a desire to do better and may express frustration at waste or inefficiency. May focus on new or more precise ways of meeting goals set | I38: 4
C39: 5. Makes specific changes in the system or in own work methods to improve performance. Examples may include doing something better, faster, at a lower cost, more efficiently, or improving quality, customer satisfaction, morale, without setting any specific goal. | I39: 4
B40: Teamwork | C40: 1. Willingly does his/her share of responsibility | I40: 5 | J40: =AVERAGE(I40:I44) -> 4.8
C41: 2. Promotes collaboration and removes barriers to teamwork and goal accomplishment across the organization. | I41: 5
C42: 3. Applies negotiation principles in arriving at win-win agreements. | I42: 5
C43: 4. Drives consensus and team ownership of decisions | I43: 5
C44: 5. Works constructively and collaboratively with others and across organizations to accomplish organizational goals and objectives. | I44: 4
B45: Service Orientation | C45: 1. Can explain and articulate organizational directions, issues and problems. | I45: 4 | J45: =AVERAGE(I45:I49) -> 4
C46: 2. Takes personal responsibility for dealing with and/or correcting customer service issues and concerns. | I46: 4
C47: 3. Initiates activities that promotes advocacy for men and women empowerment. | I47: 4
C48: 4. Participates in updating office vision, mission, mandates and strategies based on DEPED strategies and directions. | I48: 4
C49: 5. Develops and adopts service improvement program through simplified procedures that will further enhance service delivery. | I49: 4
B50: Innovation | C50: 1. Examines the root cause of problems and suggests effective solutions. Foster new ideas, processes, and suggests better ways to do things (cost and/or operational efficiency). | I50: 5 | J50: =AVERAGE(I50:I54) -> 4.8
C51: 2. Demonstrates an ability to think “beyond the box”. Continuously focuses on improving personal productivity to create higher value and results. | I51: 5
C52: 3. Promotes a creative climate and inspires co-workers to develop original ideas or solutions. | I52: 5
C53: 4. Translates creative thinking into tangible changes and solutions that improve the work unit and organization. | I53: 4
C54: 5. Uses ingenious methods to accomplish responsibilities. Demonstrates resourcefulness and the ability to succeed with minimal resources. | I54: 5
B55: Part II-B Total Score: Weighted Average (Average x 0.025) | J55: =AVERAGE(J25:J54)*0.025 -> 0.10833333
C58: ='PART I (CY 2025&SY2025-2026)'!E4 -> MC WELSON C. SOLOMON | G58: ROGER Z. ROCHAR, PhD
C60: RATEE | G60: RATER
D65: PORTIA MISSION MALLORCA, PhD CESO V
D67: APPROVING AUTHORITY

Sheet Sheet2
A1: RA | B1: OBJECTIVE | C1: TARGET | D1: WEIGHT % | E1: MOVs
A2: KRA 1: CURRICULUM & TEACHING (25%) | B2: 1. Accounted for learning outcomes (Reduced Frustration, Non-Numerates) | C2: TITLE ONLY - | D2: 0
B3: 1.1 Achieved Grade Level Ready by CRLA | C3: 85% GRL | D3: 0.05 | E3: CRLA EoSY Report
B4: 1.2 Achieved Independent Level in Phil-IRI Filipino | C4: 50% Independent | D4: 0.04 | E4: Phil-IRI Filipino Summary
B5: 1.3 Achieved Independent Level in Phil-IRI English | C5: 50% Independent | D5: 0.04 | E5: Phil-IRI English Summary
B6: 1.4 Achieved Proficient & Highly Proficient in RMA | C6: 50% Proficient | D6: 0.04 | E6: RMA School Summary
B7: 1. Performed Instructional Supervision | C7: 100% teachers observed | D7: 0.03 | E7: Observation Tool, TA Plan
B8: 1. Achieved target learner enrolled in Kindergarten | C8: 100% of target | D8: 0.02 | E8: SF1 Kinder, LIS Report
B9: 1. Prepared class program aligned with specialization | C9: 100% aligned | D9: 0.03 | E9: Approved Class Program
A10: KRA 2: LEARNING ENVIRONMENT (12%) | B10: Implemented Safe & Child-Friendly environment | C10: 100% implemented | D10: 0.03 | E10: Photos, Checklist
B11: Implemented Child Protection Policy | C11: 100% cases acted | D11: 0.03 | E11: CPC Minutes, Reports
B12: Increased participation in school activities | C12: 90% participation | D12: 0.02 | E12: Attendance, Photos
B13: Organized functional school clubs | C13: 100% functional | D13: 0.02 | E13: List of Clubs, Accomplishment
B14: Improved nutritional status of learners | C14: 100% improved | D14: 0.02 | E14: SBFP & NS Report
A15: KRA 3: LEADERSHIP (3%) | B15: Increased stakeholder participation for SBFP | C15: 100% participation | D15: 0.03 | E15: MOA, Donation Records
A16: KRA 4: GOVERNANCE & ACCOUNTABILITY (8%) | B16: Ensured implementation of SIP and WFP | C16: 100% implemented | D16: 0.03 | E16: SIP, AIP, WFP, SMEA
B17: Submitted required reports and documents | C17: 100% on time | D17: 0.02 | E17: Transmittals
B18: Crafted WFP, APP, PPMP and Budget | C18: 100% crafted | D18: 0.03 | E18: Approved WFP, APP, PPMP
A19: KRA 5: HUMAN RESOURCE (7%) | B19: Provided professional development through LAC | C19: 100% attended | D19: 0.03 | E19: LAC Plan, Attendance
B20: Implemented PRAISE reward system | C20: 2 cycles | D20: 0.02 | E20: Awards, Minutes
B21: Implemented teachers' welfare programs | C21: 100% implemented | D21: 0.02 | E21: GAD/Wellness Reports
A22: AAAA | B22: Conducted Inventory of Facilities | C22: 100% inventory | D22: 0.025 | E22: Inventory Report
B23: Ensured efficient utilization of funds | C23: 100% liquidated | D23: 0.025 | E23: Liquidation Reports
A24: TOTAL
D25: =SUM(D2:D24) -> 0.6

Sheet PART III
B1: DepEd OPCRF (ver.Feb2025), page 3 of 4
C2: PART III: SUMMARY OF RATINGS
C5: Final Performance Components | E5: Weight Allocation | F5: Obtained Score | G5: Overall Score | H5: RPMS Rating | M5: RPMS Rating Table
H6: Numerical Rating | I6: Adjectival Rating | M6: Range | N6: Numerical Rating | O6: Adjectival Rating
C7: PART I | D7: A. Commitment to Organizational Outcomes | E7: 0.6 | F7: ='PART I (CY 2025&SY2025-2026)'!U85 -> 2.4816667 | G7: =SUM(F$7:F$11) -> 4.4466667 | H7: =G7 -> 4.4466667 | I7: =IF(G7>=4.5, "Outstanding", IF(G7>=3.5, "Very Satisfactory", IF(G7>=2.5, "Satisfactory", IF(G7>=1.5, "Unsatisfactory", "Poor")))) -> Very Satisfactory | M7: 4.500-5.000 | N7: 5 | O7: Outstanding
D8: B. Innovating and Intervening Accomplishments | E8: 0.2 | F8: ='PART I (CY 2025&SY2025-2026)'!U110 -> 1 | M8: 3.500-4.499 | N8: 4 | O8: Very Satisfactory
D9: C. Organizational Effectiveness | E9: 0.15 | F9: ='PART I (CY 2025&SY2025-2026)'!U125 -> 0.75 | M9: 2.500-3.499 | N9: 3 | O9: Satisfactory
C10: PART II | D10: A. Leadership Competencies | E10: 2.5% (0.125) | F10: ='PART II'!J21 -> 0.10666667 | M10: 1.500-2.499 | N10: 2 | O10: Unsatisfactory
D11: B. Core Behavioural Competencies | E11: 2.5% (0.125) | F11: ='PART II'!J55 -> 0.10833333 | M11: 1.000-1.499 | N11: 1 | O11: Poor
C13: Ratee-Rater Agreement
C15: The signatures below confirm that the employee and his/her superior have agreed to the contents of the performance as captured in this form.
C17: Name of Employee: | D17: ='PART I (CY 2025&SY2025-2026)'!E4 -> MC WELSON C. SOLOMON | F17: Name of Superior: ROGER Z. ROCHAR, PhD
C19: Signature: | F19: Signature:
C21: Date: | F21: Date:

Sheet Sheet3

Sheet Sheet4

Sheet Sheet5

Sheet Sheet6

Sheet PART I_SampleComp
B2: OFFICE PERFORMANCE COMMITMENT AND REVIEW FORM (OPCRF) ver. Feb2025
B4: Name of Employee: REGINA N. BONDA | N4: Name of Rater: | O4: ROGER Z. ROCHAR PhD.
B5: Position/Designation: OIC PRINCIPAL | N5: Position: | O5: OIC ASDS
B6: Review Period: July 2024; July 2025 | N6: Approving Authority: | O6: PORTIA MISSION MALLORCA PhD. CESOV
B7: Strand/Bureau/Center/Service/Region/Division: SDO VICTORIAS | N7: Date of Rating | O7: 45828
B8: To improve the learning outcomes of the schools in SDO VIctorias City.
B10: PART I-A: COMMITMENT TO ORGANIZATIONAL OUTCOMES (60%) Part I-A. Commitment to Organizational Outcomes shall capture office commitments, performance, and accomplishments based on office mandates and KRAs as reflected in the official issuance on the Compendium of Office Functions. This part shall capture the contributions of the office directly targeting the Organizational Outcomes indicated in the General Appropriation Act (GAA) Programs/Subprograms, Basic Education Development Plan (BEDP) Pillars, Current Administration Agenda, and other national level commitments that are aligned with and relevant to the office KRAs. Clear attribution shall be made to ensure such alignment.
B12: TO BE ACCOMPLISHED DURING PLANNING | S12: TO BE FILLED DURING EVALUATION
B13: Organizational Outcomes Alignment | F13: Objectives (based on Office Functions) | H13: Timeline | I13: Weight Allocation | J13: Performance Targets (Target Outcome/Ouput of the Bureau/Center/Service/Division aligned with the Outcome/Output Indicators in the Organizational Outcomes) | L13: Performance Measure (Quality, Efficiency, Timeliness) | M13: Rating Scale | R13: Means of Verification (MOVs) | S13: Actual Accomplishments | T13: RATING (Q,E,T) | U13: AVERAGE (QET) | V13: WEIGHTED AVERAGE
B14: Key Result Areas (KRA) (Based on Office Mandate and Functions) | C14: Organizational Outcome Attribution (Refer to the GAA Programs/Subprogram and BEDP Pillars) | J14: Value (numerical, statistical, trend) | K14: Description (expected outcome/ output/service) | M14: 5 (Outstanding) | N14: 4 (Very Satisfactory) | O14: 3 (Satisfactory) | P14: 2 (Unsatisfactory) | Q14: 1 (Poor)
C15: GAA Programs/ Subprograms | D15: BEDP Pillars | E15: Current Administration Agenda
B16: Education Human Resource Development Program | E16: X number of policies formulated, reviewed, and issued | F16: Human Resource Development | G16: Objective 1: Ensured preparation of HR policies, guidelines, and standards that are Bureau-initiated, or may be assigned by the EXECOM for issuance; compliant with PRIME-HRM standards and national guidelines geared towards competency-based HR system within the set scheduled deadline. | H16: January to December 2024 | I16: 0.35 | L16: Quality | M16: Met all 5 indicators based on the established standards in policy formulation: a. Consistent with existing laws, policies, guidelines, requirements, and data/information as may be required by law, oversight agencies, and/or DepEd b. Consistent with agency strategic directions and appropriate with DepEd context c. Compliant with DepEd guidelines on policy development process and underwent consultations and involvement of relevant management officials, personnel, and stakeholders at all governance levels d. Provided presentation materials, press release(as needed), and briefers for Directors and Executive sponsors e. Provided with complete staff work, to include implications/scenario analysis and recommendations | N16: Met 4 out of 5 indicators based on the established standards in policy formulation | O16: Met 3 out of 5 indicators based on the established standards in policy formulation | P16: Met 2 out of 5 indicators based on the established standards in policy formulation | Q16: Only 1 out of 5 indicators is met based on the established standards in policy formulation | S16: Policy deliverables submitted followed the set standards in policy formulation and met all 5 indicators | T16: 5 | U16: =AVERAGE(T16:T18) -> 4.6666667
L17: Efficiency | M17: 100% of total number of policy deliverables submitted and/or presented to the Director for approval; commented upon by such and provided responses to said comments; and/or integrated into the proposed policy action document. | N17: 76-99% of total number of policy deliverables submitted and/or presented to the Director for approval; commented upon by such and provided responses to said comments; and/or integrated into the proposed policy action document. | O17: 51-75% of total number of policy deliverables submitted and/or presented to the Director for approval; commented upon by such and provided responses to said comments; and/or integrated into the proposed policy action document. | P17: 26-50% of total number of policy deliverables submitted and/or presented to the Director for approval; commented upon by such and provided responses to said comments; and/or integrated into the proposed policy action document. | Q17: 25 %and below of total number of policy deliverables submitted and/or presented to the Director for approval; commented upon by such and provided responses to said comments; and/or integrated into the proposed policy action document. | S17: 13 out of 15 (87%) policy deliverables were submitted and/or presented to the Director and/or EXECOM for approval | T17: 4
L18: Timeliness | M18: Endorsed to the Office of the Director before the deadline set | N18: Endorsed to the Office of the Director on the deadline set | O18: Endorsed to the Office of the Director two weeks after the deadline | P18: Endorsed to the Office of the Director one month after the deadline | Q18: Endorsed to the Office of the Director more than one month | S18: 13 policy deliberables endorsed to the Office of the Director before the deadline set | T18: 5
C19: Refer to Accountability Matrix (PREXC Indicators) | D19: Refer to Accountability Matrix (PREXC Indicators) | E19: Refer to 5-Point Agenda of the DepEd Secretary | I19: 0.2 | L19: Quality | T19: 5 | U19: =AVERAGE(T19:T21) -> 5 | V19: =U19*I19 -> 1
L20: Efficiency | T20: 5
L21: Timeliness | T21: 5
I22: 0.2 | L22: Quality | T22: 5 | U22: =AVERAGE(T22:T24) -> 5 | V22: =U22*I22 -> 1
L23: Efficiency | T23: 5
L24: Timeliness | T24: 5
I25: 0.2 | L25: Quality | T25: 5 | U25: =AVERAGE(T25:T27) -> 5 | V25: =U25*I25 -> 1
L26: Efficiency | T26: 5
L27: Timeliness | T27: 5
R37: Part I-A Total Score | V37: =SUM(V19:V27) -> 3
B40: PART I-B: INNOVATING AND INTERVENING ACCOMPLISHMENTS (20%) Part I-B. Innovating and Intervening Accomplishments shall capture the outcomes/outputs of the office that are enabling, supportive, and/or contributory to the achievement of the organizational commitments and KRAs in Part I-A. Accomplishments can be innovations, interventions, and enhancements on the processes, services, and/or outputs.
B41: TO BE FILLED IN DURING PLANNING | S41: TO BE FILLED DURING EVALUATION
B42: Key Result Areas (KRA) | F42: Objectives | H42: Timeline | I42: Weight Allocation | J42: Performance Targets (Target Outcome/Ouput of the Bureau/Center/Service/Division that are enabling, supportive, and/or contributory to the achievement of the organizational outcomes and KRAs (Part I-A)) | L42: Performance Measure (Quality, Efficiency, Timeliness) | M42: RATING SCALE | R42: Means of Verification (MOVs) | S42: Actual Results/ Accomplishments | T42: RATING (Q,E,T) | U42: AVERAGE (QET) | V42: WEIGHTED AVERAGE
J43: Value (numerical, statistical, trend) | K43: Description (expected outcome/ output/service) | M43: 5 (Outstanding) | N43: 4 (Very Satisfactory) | O43: 3 (Satisfactory) | P43: 2 (Unsatisfactory) | Q43: 1 (Poor)
B44: 2. LEARNING ENVIRONMENT | F44: : Promoted a safe, clean and healthy learning environment by implementing the following Clean and Green program. | H44: July 2024-April 2025 | I44: 0.05 | J44: 0.01 | K44: Clean and Green program implemented | L44: Quality | M44: 95% -100% implemented and sustained Clean and Green program | N44: 90% - 94% implemented and sustained Clean and Green program | O44: 85% - 89% implemented and sustained Clean and Green program | P44: 80% - 84% implemented and sustained Clean and Green program | Q44: 75% - 79% implemented and sustained Clean and Green program | R44: 1. School Memo | T44: 5 | U44: =AVERAGE(T44:T46) -> 5 | V44: =U44*I44 -> 0.25
L45: Efficiency | M45: All MOVs are submitted | N45: 4-5 MOVs are submitted | O45: 3 MOVs are submitted | P45: 2 MOVs are submitted | Q45: 1 MOV are submitted | T45: 5
F46: 1. Waste Segregation | L46: Timeliness | M46: ( Clean and Green components will be implemented throughout the year) | R46: 2. Minutes of the Meeting | T46: 5
I47: 0.05 | L47: Quality | T47: 5 | U47: =AVERAGE(T47:T49) -> 5 | V47: =U47*I47 -> 0.25
F48: 2. Project SANYOG | L48: Efficiency | R48: 3. M&E tool | T48: 5
L49: Timeliness | T49: 5
F50: 3. Edible Landscaping | I50: 0.1 | L50: Quality | R50: 4. Attendance Sheet | T50: 5 | U50: =AVERAGE(T50:T52) -> 5 | V50: =U50*I50 -> 0.5
L51: Efficiency | T51: 5
F52: 4. Gulayan sa Paaralan | L52: Timeliness | R52: 5. Accomplishment Reports | T52: 5
R54: 6. Pictures
B71: Part I-B Total Score | V71: =SUM(V44:V52) -> 1
B73: PART I-C: ORGANIZATIONAL EFFECTIVENESS (15%) Part I-C. Organizational Effectiveness shall capture accomplishments/outputs produced or attained on the aspects of Financial Stewardship, Process Improvement, and Client Satisfaction. It shall focus on the results achieved by the office that are aligned with the Performance-based Bonus (PBB) oversight requirements.
B75: TO BE FILLED IN DURING PLANNING | S75: TO BE FILLED DURING EVALUATION
B76: Organizational Effectiveness Area | F76: Objectives | J76: Timeline | K76: Weight Allocation | L76: Performance Measure (Quality, Efficiency, Timeliness) | M76: RATING SCALE | R76: Means of Verification (MOVs) | S76: Actual Results/ Accomplishments | T76: RATING (Q,E,T) | U76: AVERAGE (QET) | V76: WEIGHTED AVERAGE
M77: 5 (Outstanding) | N77: 4 (Very Satisfactory) | O77: 3 (Satisfactory) | P77: 2 (Unsatisfactory) | Q77: 1 (Poor)
B78: Financial Stewardship | F78: Utilized 98% of the budget allocation in accordance with the quarterly disbursement program with no overdraft/deficit/disallowance from oversight agency/ies | J78: Within the rating period | K78: 0.05 | L78: Quality | M78: Budget allocation disbursed within the reglementary period with no overdraft/deficit/disallowance from oversight agency/ies | N78: Budget allocation disbursed within the reglementary period with 1-2 overdraft/deficit/disallowance from oversight agency/ies | O78: Budget allocation disbursed within the reglementary period with 3-4 overdraft/deficit/disallowance from oversight agency/ies | P78: Budget allocation disbursed within the reglementary period with 5-6 overdraft/deficit/disallowance from oversight agency/ies | Q78: Budget allocation disbursed within the reglementary period with 7 or more overdraft/deficit/disallowance from oversight agency/ies | U78: =AVERAGE(T78:T80) -> #DIV/0! | V78: =U78*K78 -> #DIV/0!
L79: Efficiency | M79: Budget is utilized according to the BUR target, based on the official BUR report of the Finance Service/Section/Unit (i.e. 98% of the budget allocation is utilized within the FY) | N79: Budget is utilized with 1-5% variance from BUR target, based on the official BUR report of the Finance Service/Section/Unit (i.e. 93-97% of the budget allocation is utilized within the FY) | O79: Budget is utilized with 6-10% variance from BUR target, based on the official BUR report of the Finance Service/Section/Unit (i.e. 88-92% of the budget allocation is utilized within the FY) | P79: Budget is utilized with 11-15% variance from BUR target, based on the official BUR report of the Finance Service/Section/Unit (i.e. 83-87% of the budget allocation is utilized within the FY) | Q79: Budget is utilized with more than 15% variance from BUR target, based on the official BUR report of the Finance Service/Section/Unit (i.e. Below 83% of the budget allocation is utilized within the FY)
L80: Timeliness | M80: Quarterly basis: Budget is utilized according to the quarterly disbursement program (i.e. 98% of the quarterly BUR target is utilized by the end of each quarter) | N80: Quarterly basis: Budget is utilized with 1-5% variance from the quarterly disbursement program (i.e. 93-97% of the quarterly BUR target is utilized by the end of each quarter) | O80: Quarterly basis: Budget is utilized with 6-10% variance from the quarterly disbursement program (i.e. 88-92% of the quarterly BUR target is utilized by the end of each quarter) | P80: Quarterly basis: Budget is utilized with 11-15% variance from the quarterly disbursement program (i.e. 83-87% of the quarterly BUR target is utilized by the end of each quarter) | Q80: Quarterly basis: Budget is utilized with more than 15% variance from the quarterly disbursement program (i.e. Below 83% of the quarterly BUR target is utilized by the end of each quarter)
B81: Process improvement | F81: Streamlined core processes and management of service provisioning of frontline and other office deliverables to ensure ease of transations and/or digitalization/digitization | J81: Within the rating period | K81: 0.05 | L81: Quality | M81: Improvements/reduction on all of the service standards 1. no. of documentary requirements 2. total processing time 3. transaction cost 4. client steps/agency action steps 5. no. of signatories | N81: Improvements/reduction on 4 service standards 1. no. of documentary requirements 2. total processing time 3. transaction cost 4. client steps/agency action steps 5. no. of signatories | O81: Improvements/reduction on 2-3 service standards 1. no. of documentary requirements 2. total processing time 3. transaction cost 4. client steps/agency action steps 5. no. of signatories | P81: Improvements/reduction on 1 service standards 1. no. of documentary requirements 2. total processing time 3. transaction cost 4. client steps/agency action steps 5. no. of signatories | Q81: No change in no. of documentary requirements, total processing time, transaction cost, process steps, signatories | T81: 5 | U81: =AVERAGE(T81:T83) -> 5 | V81: =U81*K81 -> 0.25
L82: Efficiency | M82: Streamlined and/or digitized all office core processes identified in the QMS planning documents | N82: Streamlined and/or digitized 76-99% of the office core processes identified in the QMS planning documents | O82: Streamlined and/or digitized 51-75% of the office core processes identified in the QMS planning documents | P82: Streamlined and/or digitized 26-50% of the office core processes identified in the QMS planning documents | Q82: Streamlined and/or digitized 0-25% of the office core processes identified in the QMS planning documents | T82: 5
L83: Timeliness | T83: 5
B84: Client Satisfaction | F84: Achieved 100% resolution and compliance rate to #8888 and CCB complaints within the prescribed processing time (simple - 3 days; complex - 7 days; highly technical - 20 days) with at least Satisfactory overall average result on the Client Satisfaction Measurement | J84: Within the rating period | K84: 0.05 | L84: Quality | M84: 95.0% - 100% (Outstanding) overall average on the results of the Client Satisfaction Measurement (CSM) | N84: 90.9% - 94.9% (Very Satisfactory) overall average on the results of the CSM | O84: 80.0% - 89.9% (Satisfactory) overall average on the results of the CSM | P84: 60.0% - 79.9% (Fair) overall average on the results of the CSM | Q84: Below 60.0% (Poor) overall average on the results of the CSM | T84: 5 | U84: =AVERAGE(T84:T86) -> 5 | V84: =U84*K84 -> 0.25
L85: Efficiency | M85: 100% resolution and compliance rate to #8888 and CCB complaints | N85: At least 80% resolution and compliance rate to #8888 and CCB complaints | O85: At least 50% resolution and compliance rate to #8888 and CCB complaints | P85: At least 1% resolution and compliance rate to #8888 and CCB complaints | Q85: 0% resolution and compliance rate to #8888 and CCB complaints | T85: 5
L86: Timeliness | M86: Complaints acted upon and closed within prescribed processing time (simple - 3 days; complex - 7 days; highly technical - 20 days) | O86: Complaints are acted upon and closed with documented delays based on the prescribed processing time (simple - 3 days; complex - 7 days; highly technical - 20 days) | Q86: No complaint acted upon and resolved | T86: 5
B105: Part I-C Total Score | V105: =SUM(V78:V86) -> #DIV/0!
D112: RATEE | I112: RATER | N112: APPROVING AUTHORITY

Sheet PART II_SampleCom
B2: DepEd OPCRF (ver.Feb2025), page 2 of 4
B3: PART II-A: LEADERSHIP COMPETENCIES (2.5%) Part II-A. Leadership Competencies shall capture competencies expected of heads of functional offices who hold managerial and executive/supervisory positions. The Leadership Competencies expected to be demonstrated include Leading People, People Performance Management, and People Development.
B4: Competencies | C4: Behavioural Indicators | G4: Remarks/ Observations | I4: RATING | J4: AVERAGE | L4: DepEd Competencies Scale
L5: Numerical Rating | M5: Adjectival Rating | N5: Definition
B6: Leading People | C6: 1. Uses basic persuasion techniques in a discussion or presentation e.g., staff mobilization, appeals to reason and/or emotions, uses data and examples, visual aids | I6: 5 | J6: =AVERAGE(I6:I10) -> 5 | L6: 5 | M6: Role Model | N6: Behavioral indicator is consistently exhibited and is worthy of emulation.
C7: 2. Persuades, convinces or influences others, in order to have a specific impact or effect. | I7: 5 | L7: 4 | M7: Consistently Demonstrated | N7: Behavioral indicator is constantly shown.
C8: 3. “Sets a good example”, is a credible and respected leader; and demonstrates desired behavior. | I8: 5 | L8: 3 | M8: Most of the Time Demonstrated | N8: Behavioral indicator is often shown.
C9: 4. Forwards personal, professional and work unit needs and interests in an issue. | I9: 5 | L9: 2 | M9: Sometimes Demonstrated | N9: Behavioral indicator is irregularly shown.
C10: 5. Assumes a pivotal role in promoting the development of an inspiring, relevant vision for the organization and influences others to share ownership of DepEd goals, in order to create an effective work environment. | I10: 5 | L10: 1 | M10: Rarely Demonstrated | N10: Behavioral indicator is seldom shown.
B11: People Performance Management | C11: 1. Makes specific changes in the performance management system or in own work methods to improve performance (e.g. does something better, faster, at lower cost, more efficiently; improves quality, customer satisfaction, morale, revenues). | I11: 5 | J11: =AVERAGE(I11:I15) -> 5
C12: 2. Sets performance standards and measures progress of employees based on office and department targets. | I12: 5
C13: 3. Provides feedback and technical assistance such as coaching for performance improvement and action planning. | I13: 5
C14: 4. States performance expectations clearly and checks understanding and commitment. | I14: 5
C15: 5. Performs all the stages of result-based performance management system supported by evidence and required documents/forms. | I15: 5
B16: People Development | C16: 1. Improves the skills and effectiveness of individuals through employing a range of development strategies. | I16: 5 | J16: =AVERAGE(I16:I20) -> 5
C17: 2. Facilitates workforce effectiveness through coaching and motivating/developing people within a work environment that promotes mutual trust and respect. | I17: 5
C18: 3. Conceptualizes and implements learning interventions to meet identified training needs. | I18: 5
C19: 4. Does long-term coaching or training by arranging appropriate and helpful assignments, formal training, or other experiences for the purpose of supporting a person’s learning and development. | I19: 5
C20: 5. Cultivates a learning environment by structuring interactive experiences such as looking for future opportunities that are in support of achieving individual career goals. | I20: 5
B21: Part II-A : Weighted Average (Average x 0.025) | J21: =AVERAGE(J6:J20)*0.025 -> 0.125
B22: PART II-B: CORE BEHAVIOURAL COMPETENCIES (2.5%) Part II-B. Core Behavioral Competencies shall capture competencies required from all DepEd personnel in all job groups within the organization, upholding the DepEd’s core values and the Code of Conduct and Ethical Standards for Public Officials and Employees pursuant to RA 6713. They represent the way individuals embody and live the values of the organization.
B23: Competencies | C23: Behavioural Indicators | G23: Remarks/ Observations | I23: RATING | J23: AVERAGE
B25: Self-Management | C25: 1. Sets personal goals and direction, needs and development. | I25: 5 | J25: =AVERAGE(I25:I29) -> 5
C26: 2. Understands personal actions and behavior that are clear and purposive and takes into account personal goals and values congruent to that of the organization | I26: 5
C27: 3. Displays emotional maturity and enthusiasm for and is challenged by higher goals | I27: 5
C28: 4. Prioritize work tasks and schedules (through Gantt charts, checklists, etc.) to achieve goals | I28: 5
C29: 5. Sets high quality, challenging, realistic goals for self and others. | I29: 5
B30: Professionalism and Ethics | C30: 1. Demonstrate the values and behavior enshrined in the Norms and Conduct and Ethical Standards for Public Officials and Employees (RA 6713). | I30: 5 | J30: =AVERAGE(I30:I34) -> 5
C31: 2. Practice ethical and professional behavior and conduct taking into account the impact of his/her actions and decisions. | I31: 5
C32: 3. Maintains a professional image: being trustworthy, regularity of attendance and punctuality, good grooming and communication. | I32: 5
C33: 4. Makes personal sacrifices to meet the organization’s needs. | I33: 5
C34: 5. Act with a sense of urgency and responsibility to meet the organization’s needs, improve system and help others improve their effectiveness. | I34: 5
B35: Results Focus | C35: 1. Achieves results with optimal use of time and resources mist of the time. | I35: 5 | J35: =AVERAGE(I35:I39) -> 5
C36: 2. Avoids rework, mistakes and wastage through effective work methods by placing organizational needs before personal needs. | I36: 5
C37: 3. Delivers error-free outputs most of the time by conforming to standard operating procedures correctly and consistently. Able to produce very satisfactory quality of work in terms of usefulness/acceptability and completeness with no supervision required. | I37: 5
C38: 4. Expresses a desire to do better and may express frustration at waste or inefficiency. May focus on new or more precise ways of meeting goals set | I38: 5
C39: 5. Makes specific changes in the system or in own work methods to improve performance. Examples may include doing something better, faster, at a lower cost, more efficiently, or improving quality, customer satisfaction, morale, without setting any specific goal. | I39: 5
B40: Teamwork | C40: 1. Willingly does his/her share of responsibility | I40: 5 | J40: =AVERAGE(I40:I44) -> 5
C41: 2. Promotes collaboration and removes barriers to teamwork and goal accomplishment across the organization. | I41: 5
C42: 3. Applies negotiation principles in arriving at win-win agreements. | I42: 5
C43: 4. Drives consensus and team ownership of decisions | I43: 5
C44: 5. Works constructively and collaboratively with others and across organizations to accomplish organizational goals and objectives. | I44: 5
B45: Service Orientation | C45: 1. Can explain and articulate organizational directions, issues and problems. | I45: 5 | J45: =AVERAGE(I45:I49) -> 5
C46: 2. Takes personal responsibility for dealing with and/or correcting customer service issues and concerns. | I46: 5
C47: 3. Initiates activities that promotes advocacy for men and women empowerment. | I47: 5
C48: 4. Participates in updating office vision, mission, mandates and strategies based on DEPED strategies and directions. | I48: 5
C49: 5. Develops and adopts service improvement program through simplified procedures that will further enhance service delivery. | I49: 5
B50: Innovation | C50: 1. Examines the root cause of problems and suggests effective solutions. Foster new ideas, processes, and suggests better ways to do things (cost and/or operational efficiency). | I50: 5 | J50: =AVERAGE(I50:I54) -> 5
C51: 2. Demonstrates an ability to think “beyond the box”. Continuously focuses on improving personal productivity to create higher value and results. | I51: 5
C52: 3. Promotes a creative climate and inspires co-workers to develop original ideas or solutions. | I52: 5
C53: 4. Translates creative thinking into tangible changes and solutions that improve the work unit and organization. | I53: 5
C54: 5. Uses ingenious methods to accomplish responsibilities. Demonstrates resourcefulness and the ability to succeed with minimal resources. | I54: 5
B55: Part II-B Weighted Average (Average x 0.025) | J55: =AVERAGE(J25:J54)*0.025 -> 0.125
C60: RATEE | G60: RATER
D67: APPROVING AUTHORITY

Sheet PART III_SampleComp
B1: DepEd OPCRF (ver.Feb2025), page 3 of 4
C2: PART III: SUMMARY OF RATINGS
C5: Final Performance Components | E5: Weight Allocation | F5: Obtained Score | G5: Overall Score | H5: RPMS Rating | M5: RPMS Rating Table
H6: Numerical Rating | I6: Adjectival Rating | M6: Range | N6: Numerical Rating | O6: Adjectival Rating
C7: PART I | D7: A. Commitment to Organizational Outcomes | E7: 0.6 | F7: ='PART I (CY 2025&SY2025-2026)'!U40 -> 0.2 | G7: =SUM(F$7:F$11) -> #REF! | M7: 4.500-5.000 | N7: 5 | O7: Outstanding
D8: B. Innovating and Intervening Accomplishments | E8: 0.2 | F8: =#REF! -> #REF! | M8: 3.500-4.499 | N8: 4 | O8: Very Satisfactory
D9: C. Organizational Effectiveness | E9: 0.15 | F9: =#REF! -> #REF! | M9: 2.500-3.499 | N9: 3 | O9: Satisfactory
C10: PART II | D10: A. Leadership Competencies | E10: 2.5% (0.125) | F10: ='PART II'!J21 -> 0.10666667 | M10: 1.500-2.499 | N10: 2 | O10: Unsatisfactory
D11: B. Core Behavioural Competencies | E11: 2.5% (0.125) | F11: ='PART II'!J55 -> 0.10833333 | M11: 1.000-1.499 | N11: 1 | O11: Poor
C13: Ratee-Rater Agreement
C15: The signatures below confirm that the employee and his/her superior have agreed to the contents of the performance as captured in this form.
C17: Name of Employee: | F17: Name of Superior:
C19: Signature: | F19: Signature:
C21: Date: | F21: Date:

Sheet PART IV
C2: DepEd OPCRF (ver.Feb2025), page 4 of 4
C4: PART IV: IMPROVEMENT AND DEVELOPMENT PLANS
C6: Part IV-A: Office Improvement Plan
E7: Action Plan
C8: Gap Analysis (SWOT) | D8: Improvement Area | E8: General Objective | G8: Recommended Improvement Intervention | I8: Timeline | J8: Resources Needed
C12: Feedback:
C14: Part IV-B: Individual Development Plan
E15: Action Plan
C16: Strengths | D16: Improvement Needs | E16: Learning Objective (based on the developmental intervention) | G16: Recommended Developmental Intervention | I16: Timeline | J16: Resources Needed
I17: Whole Year | J17: Human Resource
C20: Feedback:
C22: ='PART I (CY 2025&SY2025-2026)'!E4 -> MC WELSON C. SOLOMON | F22: ROGER Z. ROCHAR, PhD | I22: PORTIA MISSION MALLORCA, PhD CESO V
C23: RATEE | F23: RATER | I23: APPROVING AUTHORITY
